Workbook

Sheet Overview
A1: ABA Opportunity Reports & Dashboards – Filter Criteria
A2: Generated from the deployed Salesforce metadata and live data in org ABA_Dev.
A4: Setting | B4: Value | C4: Note
A5: As of date | B5: 46303 | C5: Date the live data was read. Relative date filters (this month, current FY, next 30 days) resolve against this date. Change it to recalculate Age on the Opportunity Data sheet.
A6: Org | B6: ABA_Dev (00DgK00000bWvvVUAS) | C6: Developer Edition
A7: Fiscal year | B7: Standard, January – December | C7: Fiscal quarters equal calendar quarters
A8: Currency | B8: Amounts are SAR values from the sample CSV | C8: Org currency is USD, so Salesforce shows a $ sign
A9: Report type | B9: Opportunities (standard) | C9: All reports use Show Me = All opportunities (scope: organization)
A11: Sheet | B11: What it shows
A12: Report Catalog | B12: One row per report: purpose, folder, format, every filter, grouping, column, summary, chart and sort, and where it is used.
A13: Report Filters | B13: One row per filter condition per report, including the standard Opportunity Status and date-range filters and the filter logic.
A14: Report Fields | B14: One row per field per report, and its role (filter, date filter, row or column grouping, detail column, summary, chart).
A15: Field Usage Matrix | B15: Every field against every report, showing where each field is used.
A16: Dashboards | B16: Dashboard-level settings: folder, running user, grid, and dashboard filters with all their options.
A17: Dashboard Components | B17: One row per component: position on the grid, type, source report and that report's filters, measure, groupings, sort, gauge bands, table columns and current value.
A18: Home Page | B18: Sales app Home page regions and their components.
A19: Opportunity Data | B19: Every opportunity in the org with all reporting fields, plus a 1/0 flag showing whether it is included in each report.
A20: Report Results | B20: Record count and amount for each report, calculated with formulas from the flags, alongside the live count from Salesforce.
A21: Folders & Access | B21: Report and dashboard folders and who they are shared with.
A23: Legend | B23: Yellow fill and blue text = input you can change. Black text = formula or text taken from Salesforce.

Sheet Report Catalog
A1: Report ID | B1: Report name | C1: Column1 | D1: Column2 | E1: Column3 | F1: Column4 | G1: Description | H1: Format | I1: Report type | J1: Show Me (scope) | K1: Opportunity Status | L1: Date field | M1: Date range | N1: Date range resolved (as of 8 Oct 2026) | O1: Field filters | P1: Filter logic | Q1: Group rows by | R1: Group columns by | S1: Detail columns | T1: Summaries | U1: Custom summary formula | V1: Row limit | W1: Sort | X1: Report chart | Y1: Show details / subtotals / grand total | Z1: Used in dashboards & Home page | AA1: Salesforce report ID
A2: R01 | B2: Revenue Won – YTD by Quarter & Month | G2: Closed Won revenue this fiscal year by fiscal quarter and month. | H2: Summary | I2: Opportunity | J2: All opportunities | K2: All Opportunities | L2: Close Date | M2: Current FY | N2: 1 Jan 2026 – 31 Dec 2026 | O2: 1. Stage equals "Closed Won" | P2: AND (all conditions) | Q2: Close Date (Fiscal Quarter) → Close Month (Calendar Month) | R2: – | S2: Opportunity Name, Account Name, Opportunity Owner, Type, Amount | T2: Sum of Amount, Record Count | U2: – | V2: None | W2: Default | X2: VerticalColumn · X: Close Date · Y: Sum of Amount | Y2: true / true / true | Z2: D1: Revenue Won – YTD Home page (sidebar): report chart | AA2: 00OgK00000EysQTUAZ
A3: R02 | B3: Revenue Won – This Month (MTD) | G3: Closed Won revenue this month by salesperson. | H3: Summary | I3: Opportunity | J3: All opportunities | K3: All Opportunities | L3: Close Date | M3: Current Calendar Month | N3: 1 Oct 2026 – 31 Oct 2026 | O3: 1. Stage equals "Closed Won" | P3: AND (all conditions) | Q3: Opportunity Owner | R3: – | S3: Opportunity Name, Account Name, Amount, Close Date | T3: Sum of Amount, Record Count | U3: – | V3: None | W3: Default | X3: No chart | Y3: true / true / true | Z3: D1: Revenue Won – MTD | AA3: 00OgK00000EysQUUAZ
A4: R03 | B4: Revenue Won – This Quarter (QTD) | G4: Closed Won revenue this fiscal quarter by salesperson (gauge vs quarterly target). | H4: Summary | I4: Opportunity | J4: All opportunities | K4: All Opportunities | L4: Close Date | M4: Current FQ | N4: 1 Oct 2026 – 31 Dec 2026 | O4: 1. Stage equals "Closed Won" | P4: AND (all conditions) | Q4: Opportunity Owner | R4: – | S4: Opportunity Name, Account Name, Amount, Close Date | T4: Sum of Amount, Record Count | U4: – | V4: None | W4: Default | X4: No chart | Y4: true / true / true | Z4: D1: Revenue Won – QTD vs Target | AA4: 00OgK00000EysQVUAZ
A5: R04 | B5: Revenue Won – This Year vs Last Year | G5: Closed Won revenue by quarter, current vs previous fiscal year. | H5: Matrix | I5: Opportunity | J5: All opportunities | K5: All Opportunities | L5: Close Date | M5: Previous FY + Current FY | N5: 1 Jan 2025 – 31 Dec 2026 | O5: 1. Stage equals "Closed Won" | P5: AND (all conditions) | Q5: Close Quarter | R5: Close Date (Fiscal Year) | S5: Amount | T5: Sum of Amount, Record Count | U5: – | V5: None | W5: Default | X5: VerticalColumnGrouped · X: Close Quarter · Series: Close Date · Y: Sum of Amount · Legend Right | Y5: true / true / true | Z5: D1: Revenue by Quarter – This Year vs Last Year | AA5: 00OgK00000EysQWUAZ
A6: R05 | B6: Open Pipeline by Stage | G6: Active open pipeline by stage (excludes Deferred and Old / Archived). | H6: Summary | I6: Opportunity | J6: All opportunities | K6: Open Opportunities | L6: Close Date | M6: All Time | N6: No date limit (custom range left empty) | O6: 1. Stage not equal to "Deferred,Old / Archived" | P6: AND (all conditions) | Q6: Stage | R6: – | S6: Opportunity Name, Account Name, Opportunity Owner, Amount, Probability (%), Expected Revenue, Close Date, Next Step | T6: Sum of Amount, Sum of Expected Revenue, Record Count | U6: – | V6: None | W6: Default | X6: Funnel · X: Stage · Y: Sum of Amount · Legend Right | Y6: true / true / true | Z6: D1: Open Pipeline Value D1: Pipeline by Stage Home page (bottomLeft): report chart | AA6: 00OgK00000EysQXUAZ
A7: R06 | B7: Pipeline by Close Quarter (Next 4) | G7: Active open pipeline closing this and the next 3 fiscal quarters, by forecast category. | H7: Matrix | I7: Opportunity | J7: All opportunities | K7: Open Opportunities | L7: Close Date | M7: Current FQ + Next 3 FQ | N7: 1 Oct 2026 – 30 Sep 2027 | O7: 1. Stage not equal to "Deferred,Old / Archived" | P7: AND (all conditions) | Q7: Close Date (Fiscal Quarter) | R7: Forecast Category | S7: Amount | T7: Sum of Amount, Record Count | U7: – | V7: None | W7: Default | X7: VerticalColumnStacked · X: Close Date · Series: Forecast Category · Y: Sum of Amount · Legend Right | Y7: true / true / true | Z7: D1: Pipeline by Close Quarter | AA7: 00OgK00000EysQYUAZ
A8: R07 | B8: Pipeline by Salesperson & Stage | G8: Active open pipeline by salesperson and stage. | H8: Matrix | I8: Opportunity | J8: All opportunities | K8: Open Opportunities | L8: Close Date | M8: All Time | N8: No date limit (custom range left empty) | O8: 1. Stage not equal to "Deferred,Old / Archived" | P8: AND (all conditions) | Q8: Opportunity Owner | R8: Stage | S8: Amount | T8: Sum of Amount, Record Count | U8: – | V8: None | W8: Default | X8: HorizontalBarStacked · X: Opportunity Owner · Series: Stage · Y: Sum of Amount · Legend Right | Y8: true / true / true | Z8: D2: Pipeline by Salesperson & Stage | AA8: 00OgK00000EysQcUAJ
A9: R08 | B9: Revenue Won by Salesperson – YTD | G9: Leaderboard: Closed Won revenue this fiscal year by salesperson. | H9: Summary | I9: Opportunity | J9: All opportunities | K9: All Opportunities | L9: Close Date | M9: Current FY | N9: 1 Jan 2026 – 31 Dec 2026 | O9: 1. Stage equals "Closed Won" | P9: AND (all conditions) | Q9: Opportunity Owner, sorted by aggregate Amount desc | R9: – | S9: Opportunity Name, Account Name, Amount, Close Date | T9: Sum of Amount, Record Count | U9: – | V9: None | W9: Default | X9: HorizontalBar · X: Opportunity Owner · Y: Sum of Amount | Y9: true / true / true | Z9: D2: Revenue Won by Salesperson Home page (sidebar): report chart | AA9: 00OgK00000EysQdUAJ
A10: R09 | B10: Win Rate by Salesperson – YTD | G10: Win rate (won / closed) this fiscal year by salesperson. | H10: Summary | I10: Opportunity | J10: All opportunities | K10: Closed Opportunities | L10: Close Date | M10: Current FY | N10: 1 Jan 2026 – 31 Dec 2026 | O10: None | P10: AND (all conditions) | Q10: Opportunity Owner | R10: – | S10: Opportunity Name, Stage, Amount, Won, Closed | T10: Sum of Amount, Record Count | U10: Win Rate % = WON:SUM / CLOSED:SUM (percent, 0 dp) | V10: None | W10: Default | X10: No chart | Y10: true / true / true | Z10: D1: Win Rate YTD D2: Win Rate by Salesperson | AA10: 00OgK00000EysQeUAJ
A11: R10 | B11: Win-Loss Analysis by Reason – YTD | G11: Closed opportunities this fiscal year by outcome and win/loss reason. | H11: Summary | I11: Opportunity | J11: All opportunities | K11: Closed Opportunities | L11: Close Date | M11: Current FY | N11: 1 Jan 2026 – 31 Dec 2026 | O11: None | P11: AND (all conditions) | Q11: Stage → Win/Loss Reason | R11: – | S11: Opportunity Name, Account Name, Opportunity Owner, Amount, Win/Loss Details | T11: Sum of Amount, Record Count | U11: – | V11: None | W11: Default | X11: HorizontalBarStacked · X: Stage · Series: Win/Loss Reason · Y: Sum of Amount · Legend Right | Y11: true / true / true | Z11: Report only | AA11: 00OgK00000EysQhUAJ
A12: R10a | B12: Why We Win – YTD | G12: Dashboard source: Closed Won this fiscal year by win reason. | H12: Summary | I12: Opportunity | J12: All opportunities | K12: All Opportunities | L12: Close Date | M12: Current FY | N12: 1 Jan 2026 – 31 Dec 2026 | O12: 1. Stage equals "Closed Won" | P12: AND (all conditions) | Q12: Win/Loss Reason | R12: – | S12: Opportunity Name, Account Name, Opportunity Owner, Amount, Win/Loss Details | T12: Sum of Amount, Record Count | U12: – | V12: None | W12: Default | X12: Donut · X: Win/Loss Reason · Y: Sum of Amount · Legend Right | Y12: true / true / true | Z12: D2: Why We Win Home page (bottomRight): report chart | AA12: 00OgK00000EysQfUAJ
A13: R10b | B13: Why We Lose – YTD | G13: Dashboard source: Closed Lost this fiscal year by loss reason. | H13: Summary | I13: Opportunity | J13: All opportunities | K13: All Opportunities | L13: Close Date | M13: Current FY | N13: 1 Jan 2026 – 31 Dec 2026 | O13: 1. Stage equals "Closed Lost" | P13: AND (all conditions) | Q13: Win/Loss Reason | R13: – | S13: Opportunity Name, Account Name, Opportunity Owner, Amount, Win/Loss Details | T13: Sum of Amount, Record Count | U13: – | V13: None | W13: Default | X13: Donut · X: Win/Loss Reason · Y: Sum of Amount · Legend Right | Y13: true / true / true | Z13: D2: Why We Lose | AA13: 00OgK00000EysQgUAJ
... A21: R18 | B21: Average Deal Size & Sales Cycle | G21: Average deal size and age (days) of deals won in the last 365 days. | H21: Summary | I21: Opportunity | J21: All opportunities | K21: All Opportunities | L21: Close Date | M21: All Time | N21: No date limit (custom range left empty) | O21: 1. Stage equals "Closed Won" 2. Close Date equals "LAST_N_DAYS:365" | P21: AND (all conditions) | Q21: Opportunity Owner | R21: – | S21: Opportunity Name, Amount, Age, Created Date, Close Date | T21: Average of Amount, Average of Age, Record Count | U21: – | V21: None | W21: Default | X21: No chart | Y21: true / true / true | Z21: Report only | AA21: 00OgK00000EysQmUAJ

Sheet Report Filters
A1: Report ID | B1: Report name | C1: Filter # | D1: Filter kind | E1: Field | F1: Field API name | G1: Operator | H1: Value | I1: Resolved value (as of 8 Oct 2026) | J1: Filter logic | K1: Meaning
A2: R01 | B2: Revenue Won – YTD by Quarter & Month | C2: S1 | D2: Standard filter: Show Me | E2: Scope | F2: scope | G2: equals | H2: All opportunities | I2: All opportunities | K2: Every user's opportunities are included, not just the viewer's.
A3: R01 | B3: Revenue Won – YTD by Quarter & Month | C3: S2 | D3: Standard filter: Opportunity Status | E3: Opportunity Status | F3: open | G3: equals | H3: All Opportunities | I3: All Opportunities | K3: Open and closed opportunities.
A4: R01 | B4: Revenue Won – YTD by Quarter & Month | C4: S3 | D4: Standard filter: Date range | E4: Close Date | F4: CLOSE_DATE | G4: within | H4: Current FY | I4: 1 Jan 2026 – 31 Dec 2026 | K4: Close Date falls in current fy.
A5: R01 | B5: Revenue Won – YTD by Quarter & Month | C5: 1 | D5: Field filter | E5: Stage | F5: STAGE_NAME | G5: equals | H5: Closed Won | I5: Closed Won | J5: AND | K5: Stage is Closed Won.
A6: R02 | B6: Revenue Won – This Month (MTD) | C6: S1 | D6: Standard filter: Show Me | E6: Scope | F6: scope | G6: equals | H6: All opportunities | I6: All opportunities | K6: Every user's opportunities are included, not just the viewer's.
A7: R02 | B7: Revenue Won – This Month (MTD) | C7: S2 | D7: Standard filter: Opportunity Status | E7: Opportunity Status | F7: open | G7: equals | H7: All Opportunities | I7: All Opportunities | K7: Open and closed opportunities.
A8: R02 | B8: Revenue Won – This Month (MTD) | C8: S3 | D8: Standard filter: Date range | E8: Close Date | F8: CLOSE_DATE | G8: within | H8: Current Calendar Month | I8: 1 Oct 2026 – 31 Oct 2026 | K8: Close Date falls in current calendar month.
A9: R02 | B9: Revenue Won – This Month (MTD) | C9: 1 | D9: Field filter | E9: Stage | F9: STAGE_NAME | G9: equals | H9: Closed Won | I9: Closed Won | J9: AND | K9: Stage is Closed Won.
A10: R03 | B10: Revenue Won – This Quarter (QTD) | C10: S1 | D10: Standard filter: Show Me | E10: Scope | F10: scope | G10: equals | H10: All opportunities | I10: All opportunities | K10: Every user's opportunities are included, not just the viewer's.
A11: R03 | B11: Revenue Won – This Quarter (QTD) | C11: S2 | D11: Standard filter: Opportunity Status | E11: Opportunity Status | F11: open | G11: equals | H11: All Opportunities | I11: All Opportunities | K11: Open and closed opportunities.
A12: R03 | B12: Revenue Won – This Quarter (QTD) | C12: S3 | D12: Standard filter: Date range | E12: Close Date | F12: CLOSE_DATE | G12: within | H12: Current FQ | I12: 1 Oct 2026 – 31 Dec 2026 | K12: Close Date falls in current fq.
A13: R03 | B13: Revenue Won – This Quarter (QTD) | C13: 1 | D13: Field filter | E13: Stage | F13: STAGE_NAME | G13: equals | H13: Closed Won | I13: Closed Won | J13: AND | K13: Stage is Closed Won.
A14: R04 | B14: Revenue Won – This Year vs Last Year | C14: S1 | D14: Standard filter: Show Me | E14: Scope | F14: scope | G14: equals | H14: All opportunities | I14: All opportunities | K14: Every user's opportunities are included, not just the viewer's.
A15: R04 | B15: Revenue Won – This Year vs Last Year | C15: S2 | D15: Standard filter: Opportunity Status | E15: Opportunity Status | F15: open | G15: equals | H15: All Opportunities | I15: All Opportunities | K15: Open and closed opportunities.
A16: R04 | B16: Revenue Won – This Year vs Last Year | C16: S3 | D16: Standard filter: Date range | E16: Close Date | F16: CLOSE_DATE | G16: within | H16: Previous FY + Current FY | I16: 1 Jan 2025 – 31 Dec 2026 | K16: Close Date falls in previous fy + current fy.
A17: R04 | B17: Revenue Won – This Year vs Last Year | C17: 1 | D17: Field filter | E17: Stage | F17: STAGE_NAME | G17: equals | H17: Closed Won | I17: Closed Won | J17: AND | K17: Stage is Closed Won.
A18: R05 | B18: Open Pipeline by Stage | C18: S1 | D18: Standard filter: Show Me | E18: Scope | F18: scope | G18: equals | H18: All opportunities | I18: All opportunities | K18: Every user's opportunities are included, not just the viewer's.
A19: R05 | B19: Open Pipeline by Stage | C19: S2 | D19: Standard filter: Opportunity Status | E19: Opportunity Status | F19: open | G19: equals | H19: Open Opportunities | I19: Open Opportunities | K19: Only opportunities that are not closed.
A20: R05 | B20: Open Pipeline by Stage | C20: S3 | D20: Standard filter: Date range | E20: Close Date | F20: CLOSE_DATE | G20: within | H20: All Time | I20: No date limit (custom range left empty) | K20: Close Date falls in all time.
A21: R05 | B21: Open Pipeline by Stage | C21: 1 | D21: Field filter | E21: Stage | F21: STAGE_NAME | G21: not equal to | H21: Deferred,Old / Archived | I21: Deferred,Old / Archived | J21: AND | K21: Stage is not Deferred or Old / Archived.
A22: R06 | B22: Pipeline by Close Quarter (Next 4) | C22: S1 | D22: Standard filter: Show Me | E22: Scope | F22: scope | G22: equals | H22: All opportunities | I22: All opportunities | K22: Every user's opportunities are included, not just the viewer's.
A23: R06 | B23: Pipeline by Close Quarter (Next 4) | C23: S2 | D23: Standard filter: Opportunity Status | E23: Opportunity Status | F23: open | G23: equals | H23: Open Opportunities | I23: Open Opportunities | K23: Only opportunities that are not closed.
A24: R06 | B24: Pipeline by Close Quarter (Next 4) | C24: S3 | D24: Standard filter: Date range | E24: Close Date | F24: CLOSE_DATE | G24: within | H24: Current FQ + Next 3 FQ | I24: 1 Oct 2026 – 30 Sep 2027 | K24: Close Date falls in current fq + next 3 fq.
A25: R06 | B25: Pipeline by Close Quarter (Next 4) | C25: 1 | D25: Field filter | E25: Stage | F25: STAGE_NAME | G25: not equal to | H25: Deferred,Old / Archived | I25: Deferred,Old / Archived | J25: AND | K25: Stage is not Deferred or Old / Archived.
A26: R07 | B26: Pipeline by Salesperson & Stage | C26: S1 | D26: Standard filter: Show Me | E26: Scope | F26: scope | G26: equals | H26: All opportunities | I26: All opportunities | K26: Every user's opportunities are included, not just the viewer's.
A27: R07 | B27: Pipeline by Salesperson & Stage | C27: S2 | D27: Standard filter: Opportunity Status | E27: Opportunity Status | F27: open | G27: equals | H27: Open Opportunities | I27: Open Opportunities | K27: Only opportunities that are not closed.
A28: R07 | B28: Pipeline by Salesperson & Stage | C28: S3 | D28: Standard filter: Date range | E28: Close Date | F28: CLOSE_DATE | G28: within | H28: All Time | I28: No date limit (custom range left empty) | K28: Close Date falls in all time.
A29: R07 | B29: Pipeline by Salesperson & Stage | C29: 1 | D29: Field filter | E29: Stage | F29: STAGE_NAME | G29: not equal to | H29: Deferred,Old / Archived | I29: Deferred,Old / Archived | J29: AND | K29: Stage is not Deferred or Old / Archived.
A30: R08 | B30: Revenue Won by Salesperson – YTD | C30: S1 | D30: Standard filter: Show Me | E30: Scope | F30: scope | G30: equals | H30: All opportunities | I30: All opportunities | K30: Every user's opportunities are included, not just the viewer's.
A31: R08 | B31: Revenue Won by Salesperson – YTD | C31: S2 | D31: Standard filter: Opportunity Status | E31: Opportunity Status | F31: open | G31: equals | H31: All Opportunities | I31: All Opportunities | K31: Open and closed opportunities.
A32: R08 | B32: Revenue Won by Salesperson – YTD | C32: S3 | D32: Standard filter: Date range | E32: Close Date | F32: CLOSE_DATE | G32: within | H32: Current FY | I32: 1 Jan 2026 – 31 Dec 2026 | K32: Close Date falls in current fy.
A33: R08 | B33: Revenue Won by Salesperson – YTD | C33: 1 | D33: Field filter | E33: Stage | F33: STAGE_NAME | G33: equals | H33: Closed Won | I33: Closed Won | J33: AND | K33: Stage is Closed Won.
A34: R09 | B34: Win Rate by Salesperson – YTD | C34: S1 | D34: Standard filter: Show Me | E34: Scope | F34: scope | G34: equals | H34: All opportunities | I34: All opportunities | K34: Every user's opportunities are included, not just the viewer's.
A35: R09 | B35: Win Rate by Salesperson – YTD | C35: S2 | D35: Standard filter: Opportunity Status | E35: Opportunity Status | F35: open | G35: equals | H35: Closed Opportunities | I35: Closed Opportunities | K35: Only Closed Won and Closed Lost opportunities.
A36: R09 | B36: Win Rate by Salesperson – YTD | C36: S3 | D36: Standard filter: Date range | E36: Close Date | F36: CLOSE_DATE | G36: within | H36: Current FY | I36: 1 Jan 2026 – 31 Dec 2026 | K36: Close Date falls in current fy.
A37: R10 | B37: Win-Loss Analysis by Reason – YTD | C37: S1 | D37: Standard filter: Show Me | E37: Scope | F37: scope | G37: equals | H37: All opportunities | I37: All opportunities | K37: Every user's opportunities are included, not just the viewer's.
A38: R10 | B38: Win-Loss Analysis by Reason – YTD | C38: S2 | D38: Standard filter: Opportunity Status | E38: Opportunity Status | F38: open | G38: equals | H38: Closed Opportunities | I38: Closed Opportunities | K38: Only Closed Won and Closed Lost opportunities.
A39: R10 | B39: Win-Loss Analysis by Reason – YTD | C39: S3 | D39: Standard filter: Date range | E39: Close Date | F39: CLOSE_DATE | G39: within | H39: Current FY | I39: 1 Jan 2026 – 31 Dec 2026 | K39: Close Date falls in current fy.
A40: R10a | B40: Why We Win – YTD | C40: S1 | D40: Standard filter: Show Me | E40: Scope | F40: scope | G40: equals | H40: All opportunities | I40: All opportunities | K40: Every user's opportunities are included, not just the viewer's.
A41: R10a | B41: Why We Win – YTD | C41: S2 | D41: Standard filter: Opportunity Status | E41: Opportunity Status | F41: open | G41: equals | H41: All Opportunities | I41: All Opportunities | K41: Open and closed opportunities.
A42: R10a | B42: Why We Win – YTD | C42: S3 | D42: Standard filter: Date range | E42: Close Date | F42: CLOSE_DATE | G42: within | H42: Current FY | I42: 1 Jan 2026 – 31 Dec 2026 | K42: Close Date falls in current fy.
A43: R10a | B43: Why We Win – YTD | C43: 1 | D43: Field filter | E43: Stage | F43: STAGE_NAME | G43: equals | H43: Closed Won | I43: Closed Won | J43: AND | K43: Stage is Closed Won.
A44: R10b | B44: Why We Lose – YTD | C44: S1 | D44: Standard filter: Show Me | E44: Scope | F44: scope | G44: equals | H44: All opportunities | I44: All opportunities | K44: Every user's opportunities are included, not just the viewer's.
A45: R10b | B45: Why We Lose – YTD | C45: S2 | D45: Standard filter: Opportunity Status | E45: Opportunity Status | F45: open | G45: equals | H45: All Opportunities | I45: All Opportunities | K45: Open and closed opportunities.
A46: R10b | B46: Why We Lose – YTD | C46: S3 | D46: Standard filter: Date range | E46: Close Date | F46: CLOSE_DATE | G46: within | H46: Current FY | I46: 1 Jan 2026 – 31 Dec 2026 | K46: Close Date falls in current fy.
A47: R10b | B47: Why We Lose – YTD | C47: 1 | D47: Field filter | E47: Stage | F47: STAGE_NAME | G47: equals | H47: Closed Lost | I47: Closed Lost | J47: AND | K47: Stage is Closed Lost.
A48: R11 | B48: Closing in Next 30 Days | C48: S1 | D48: Standard filter: Show Me | E48: Scope | F48: scope | G48: equals | H48: All opportunities | I48: All opportunities | K48: Every user's opportunities are included, not just the viewer's.
A49: R11 | B49: Closing in Next 30 Days | C49: S2 | D49: Standard filter: Opportunity Status | E49: Opportunity Status | F49: open | G49: equals | H49: Open Opportunities | I49: Open Opportunities | K49: Only opportunities that are not closed.
A50: R11 | B50: Closing in Next 30 Days | C50: S3 | D50: Standard filter: Date range | E50: Close Date | F50: CLOSE_DATE | G50: within | H50: Next 30 Days | I50: Rolling: the next 30 days from today | K50: Close Date falls in next 30 days.
A51: R11 | B51: Closing in Next 30 Days | C51: 1 | D51: Field filter | E51: Stage | F51: STAGE_NAME | G51: equals | H51: Proposal Submitted,Negotiation,Verbal Award | I51: Proposal Submitted,Negotiation,Verbal Award | J51: AND | K51: Stage is Proposal Submitted or Negotiation or Verbal Award.
A52: R12 | B52: Overdue & Stale Opportunities | C52: S1 | D52: Standard filter: Show Me | E52: Scope | F52: scope | G52: equals | H52: All opportunities | I52: All opportunities | K52: Every user's opportunities are included, not just the viewer's.
A53: R12 | B53: Overdue & Stale Opportunities | C53: S2 | D53: Standard filter: Opportunity Status | E53: Opportunity Status | F53: open | G53: equals | H53: Open Opportunities | I53: Open Opportunities | K53: Only opportunities that are not closed.
A54: R12 | B54: Overdue & Stale Opportunities | C54: S3 | D54: Standard filter: Date range | E54: Close Date | F54: CLOSE_DATE | G54: within | H54: All Time | I54: No date limit (custom range left empty) | K54: Close Date falls in all time.
A55: R12 | B55: Overdue & Stale Opportunities | C55: 1 | D55: Field filter | E55: Stage | F55: STAGE_NAME | G55: not equal to | H55: Deferred,Old / Archived | I55: Deferred,Old / Archived | J55: 1 AND (2 OR 3) | K55: Stage is not Deferred or Old / Archived.
A56: R12 | B56: Overdue & Stale Opportunities | C56: 2 | D56: Field filter | E56: Close Date | F56: CLOSE_DATE | G56: less than | H56: TODAY | I56: 8 Oct 2026 | J56: 1 AND (2 OR 3) | K56: Close Date is less than TODAY.
A57: R12 | B57: Overdue & Stale Opportunities | C57: 3 | D57: Field filter | E57: Last Activity | F57: LAST_ACTIVITY | G57: less than | H57: LAST_N_DAYS:30 | I57: before 8 Sep 2026 | J57: 1 AND (2 OR 3) | K57: Last Activity is less than LAST_N_DAYS:30.
A58: R13 | B58: Deferred Opportunities | C58: S1 | D58: Standard filter: Show Me | E58: Scope | F58: scope | G58: equals | H58: All opportunities | I58: All opportunities | K58: Every user's opportunities are included, not just the viewer's.
A59: R13 | B59: Deferred Opportunities | C59: S2 | D59: Standard filter: Opportunity Status | E59: Opportunity Status | F59: open | G59: equals | H59: All Opportunities | I59: All Opportunities | K59: Open and closed opportunities.
A60: R13 | B60: Deferred Opportunities | C60: S3 | D60: Standard filter: Date range | E60: Close Date | F60: CLOSE_DATE | G60: within | H60: All Time | I60: No date limit (custom range left empty) | K60: Close Date falls in all time.
A61: R13 | B61: Deferred Opportunities | C61: 1 | D61: Field filter | E61: Stage | F61: STAGE_NAME | G61: equals | H61: Deferred | I61: Deferred | J61: AND | K61: Stage is Deferred.
A62: R14 | B62: Revenue & Pipeline by Type | C62: S1 | D62: Standard filter: Show Me | E62: Scope | F62: scope | G62: equals | H62: All opportunities | I62: All opportunities | K62: Every user's opportunities are included, not just the viewer's.
A63: R14 | B63: Revenue & Pipeline by Type | C63: S2 | D63: Standard filter: Opportunity Status | E63: Opportunity Status | F63: open | G63: equals | H63: All Opportunities | I63: All Opportunities | K63: Open and closed opportunities.
A64: R14 | B64: Revenue & Pipeline by Type | C64: S3 | D64: Standard filter: Date range | E64: Close Date | F64: CLOSE_DATE | G64: within | H64: Current FY | I64: 1 Jan 2026 – 31 Dec 2026 | K64: Close Date falls in current fy.
A65: R14 | B65: Revenue & Pipeline by Type | C65: 1 | D65: Field filter | E65: Stage | F65: STAGE_NAME | G65: not equal to | H65: Closed Lost,Deferred,Old / Archived | I65: Closed Lost,Deferred,Old / Archived | J65: AND | K65: Stage is not Closed Lost or Deferred or Old / Archived.
A66: R15 | B66: Revenue by Lead Source & Campaign | C66: S1 | D66: Standard filter: Show Me | E66: Scope | F66: scope | G66: equals | H66: All opportunities | I66: All opportunities | K66: Every user's opportunities are included, not just the viewer's.
A67: R15 | B67: Revenue by Lead Source & Campaign | C67: S2 | D67: Standard filter: Opportunity Status | E67: Opportunity Status | F67: open | G67: equals | H67: All Opportunities | I67: All Opportunities | K67: Open and closed opportunities.
A68: R15 | B68: Revenue by Lead Source & Campaign | C68: S3 | D68: Standard filter: Date range | E68: Close Date | F68: CLOSE_DATE | G68: within | H68: Current FY | I68: 1 Jan 2026 – 31 Dec 2026 | K68: Close Date falls in current fy.
A69: R15 | B69: Revenue by Lead Source & Campaign | C69: 1 | D69: Field filter | E69: Stage | F69: STAGE_NAME | G69: equals | H69: Closed Won | I69: Closed Won | J69: AND | K69: Stage is Closed Won.
A70: R16 | B70: Revenue by Industry & Country | C70: S1 | D70: Standard filter: Show Me | E70: Scope | F70: scope | G70: equals | H70: All opportunities | I70: All opportunities | K70: Every user's opportunities are included, not just the viewer's.
A71: R16 | B71: Revenue by Industry & Country | C71: S2 | D71: Standard filter: Opportunity Status | E71: Opportunity Status | F71: open | G71: equals | H71: All Opportunities | I71: All Opportunities | K71: Open and closed opportunities.
A72: R16 | B72: Revenue by Industry & Country | C72: S3 | D72: Standard filter: Date range | E72: Close Date | F72: CLOSE_DATE | G72: within | H72: Current FY | I72: 1 Jan 2026 – 31 Dec 2026 | K72: Close Date falls in current fy.
A73: R16 | B73: Revenue by Industry & Country | C73: 1 | D73: Field filter | E73: Stage | F73: STAGE_NAME | G73: equals | H73: Closed Won | I73: Closed Won | J73: AND | K73: Stage is Closed Won.
A74: R17 | B74: Upcoming Proposal Submissions | C74: S1 | D74: Standard filter: Show Me | E74: Scope | F74: scope | G74: equals | H74: All opportunities | I74: All opportunities | K74: Every user's opportunities are included, not just the viewer's.
A75: R17 | B75: Upcoming Proposal Submissions | C75: S2 | D75: Standard filter: Opportunity Status | E75: Opportunity Status | F75: open | G75: equals | H75: Open Opportunities | I75: Open Opportunities | K75: Only opportunities that are not closed.
A76: R17 | B76: Upcoming Proposal Submissions | C76: S3 | D76: Standard filter: Date range | E76: Proposal Submission Date | F76: Opportunity.Proposal_Submission_Date__c | G76: within | H76: Next 30 Days | I76: Rolling: the next 30 days from today | K76: Proposal Submission Date falls in next 30 days.
A77: R18 | B77: Average Deal Size & Sales Cycle | C77: S1 | D77: Standard filter: Show Me | E77: Scope | F77: scope | G77: equals | H77: All opportunities | I77: All opportunities | K77: Every user's opportunities are included, not just the viewer's.
A78: R18 | B78: Average Deal Size & Sales Cycle | C78: S2 | D78: Standard filter: Opportunity Status | E78: Opportunity Status | F78: open | G78: equals | H78: All Opportunities | I78: All Opportunities | K78: Open and closed opportunities.
A79: R18 | B79: Average Deal Size & Sales Cycle | C79: S3 | D79: Standard filter: Date range | E79: Close Date | F79: CLOSE_DATE | G79: within | H79: All Time | I79: No date limit (custom range left empty) | K79: Close Date falls in all time.
A80: R18 | B80: Average Deal Size & Sales Cycle | C80: 1 | D80: Field filter | E80: Stage | F80: STAGE_NAME | G80: equals | H80: Closed Won | I80: Closed Won | J80: AND | K80: Stage is Closed Won.
A81: R18 | B81: Average Deal Size & Sales Cycle | C81: 2 | D81: Field filter | E81: Close Date | F81: CLOSE_DATE | G81: equals | H81: LAST_N_DAYS:365 | I81: 8 Oct 2025 – 8 Oct 2026 | J81: AND | K81: Close Date is LAST_N_DAYS:365.

Sheet Report Fields
A1: Report ID | B1: Report name | C1: Role | D1: Order | E1: Field | F1: Field API name | G1: Aggregate / granularity | H1: Sort
A2: R01 | B2: Revenue Won – YTD by Quarter & Month | C2: Field filter | E2: Stage | F2: STAGE_NAME | G2: equals Closed Won
A3: R01 | B3: Revenue Won – YTD by Quarter & Month | C3: Date filter | E3: Close Date | F3: CLOSE_DATE | G3: Current FY
A4: R01 | B4: Revenue Won – YTD by Quarter & Month | C4: Group rows by | D4: 1 | E4: Close Date | F4: CLOSE_DATE | G4: Fiscal Quarter | H4: Asc
A5: R01 | B5: Revenue Won – YTD by Quarter & Month | C5: Group rows by | D5: 2 | E5: Close Month | F5: CLOSE_MONTH | G5: Calendar Month | H5: Asc
A6: R01 | B6: Revenue Won – YTD by Quarter & Month | C6: Detail column | D6: 1 | E6: Opportunity Name | F6: OPPORTUNITY_NAME
A7: R01 | B7: Revenue Won – YTD by Quarter & Month | C7: Detail column | D7: 2 | E7: Account Name | F7: ACCOUNT_NAME
A8: R01 | B8: Revenue Won – YTD by Quarter & Month | C8: Detail column | D8: 3 | E8: Opportunity Owner | F8: FULL_NAME
A9: R01 | B9: Revenue Won – YTD by Quarter & Month | C9: Detail column | D9: 4 | E9: Type | F9: TYPE
A10: R01 | B10: Revenue Won – YTD by Quarter & Month | C10: Detail column | D10: 5 | E10: Amount | F10: AMOUNT | G10: Sum
A11: R01 | B11: Revenue Won – YTD by Quarter & Month | C11: Chart X-axis | E11: Close Date | F11: CLOSE_DATE | G11: VerticalColumn
A12: R02 | B12: Revenue Won – This Month (MTD) | C12: Field filter | E12: Stage | F12: STAGE_NAME | G12: equals Closed Won
A13: R02 | B13: Revenue Won – This Month (MTD) | C13: Date filter | E13: Close Date | F13: CLOSE_DATE | G13: Current Calendar Month
A14: R02 | B14: Revenue Won – This Month (MTD) | C14: Group rows by | D14: 1 | E14: Opportunity Owner | F14: FULL_NAME | H14: Asc
A15: R02 | B15: Revenue Won – This Month (MTD) | C15: Detail column | D15: 1 | E15: Opportunity Name | F15: OPPORTUNITY_NAME
A16: R02 | B16: Revenue Won – This Month (MTD) | C16: Detail column | D16: 2 | E16: Account Name | F16: ACCOUNT_NAME
A17: R02 | B17: Revenue Won – This Month (MTD) | C17: Detail column | D17: 3 | E17: Amount | F17: AMOUNT | G17: Sum
A18: R02 | B18: Revenue Won – This Month (MTD) | C18: Detail column | D18: 4 | E18: Close Date | F18: CLOSE_DATE
A19: R03 | B19: Revenue Won – This Quarter (QTD) | C19: Field filter | E19: Stage | F19: STAGE_NAME | G19: equals Closed Won
A20: R03 | B20: Revenue Won – This Quarter (QTD) | C20: Date filter | E20: Close Date | F20: CLOSE_DATE | G20: Current FQ
A21: R03 | B21: Revenue Won – This Quarter (QTD) | C21: Group rows by | D21: 1 | E21: Opportunity Owner | F21: FULL_NAME | H21: Asc
A22: R03 | B22: Revenue Won – This Quarter (QTD) | C22: Detail column | D22: 1 | E22: Opportunity Name | F22: OPPORTUNITY_NAME
A23: R03 | B23: Revenue Won – This Quarter (QTD) | C23: Detail column | D23: 2 | E23: Account Name | F23: ACCOUNT_NAME
A24: R03 | B24: Revenue Won – This Quarter (QTD) | C24: Detail column | D24: 3 | E24: Amount | F24: AMOUNT | G24: Sum
A25: R03 | B25: Revenue Won – This Quarter (QTD) | C25: Detail column | D25: 4 | E25: Close Date | F25: CLOSE_DATE
A26: R04 | B26: Revenue Won – This Year vs Last Year | C26: Field filter | E26: Stage | F26: STAGE_NAME | G26: equals Closed Won
A27: R04 | B27: Revenue Won – This Year vs Last Year | C27: Date filter | E27: Close Date | F27: CLOSE_DATE | G27: Previous FY + Current FY
A28: R04 | B28: Revenue Won – This Year vs Last Year | C28: Group rows by | D28: 1 | E28: Close Quarter | F28: Opportunity.Close_Quarter__c | H28: Asc
A29: R04 | B29: Revenue Won – This Year vs Last Year | C29: Group columns by | D29: 1 | E29: Close Date | F29: CLOSE_DATE | G29: Fiscal Year | H29: Asc
A30: R04 | B30: Revenue Won – This Year vs Last Year | C30: Detail column | D30: 1 | E30: Amount | F30: AMOUNT | G30: Sum
A31: R04 | B31: Revenue Won – This Year vs Last Year | C31: Chart X-axis | E31: Close Quarter | F31: Opportunity.Close_Quarter__c | G31: VerticalColumnGrouped
A32: R04 | B32: Revenue Won – This Year vs Last Year | C32: Chart series | E32: Close Date | F32: CLOSE_DATE | G32: VerticalColumnGrouped
A33: R05 | B33: Open Pipeline by Stage | C33: Field filter | E33: Stage | F33: STAGE_NAME | G33: not equal to Deferred,Old / Archived
A34: R05 | B34: Open Pipeline by Stage | C34: Date filter | E34: Close Date | F34: CLOSE_DATE | G34: All Time
A35: R05 | B35: Open Pipeline by Stage | C35: Group rows by | D35: 1 | E35: Stage | F35: STAGE_NAME | H35: Asc
A36: R05 | B36: Open Pipeline by Stage | C36: Detail column | D36: 1 | E36: Opportunity Name | F36: OPPORTUNITY_NAME
A37: R05 | B37: Open Pipeline by Stage | C37: Detail column | D37: 2 | E37: Account Name | F37: ACCOUNT_NAME
A38: R05 | B38: Open Pipeline by Stage | C38: Detail column | D38: 3 | E38: Opportunity Owner | F38: FULL_NAME
A39: R05 | B39: Open Pipeline by Stage | C39: Detail column | D39: 4 | E39: Amount | F39: AMOUNT | G39: Sum
A40: R05 | B40: Open Pipeline by Stage | C40: Detail column | D40: 5 | E40: Probability (%) | F40: PROBABILITY
A41: R05 | B41: Open Pipeline by Stage | C41: Detail column | D41: 6 | E41: Expected Revenue | F41: EXP_AMOUNT | G41: Sum
A42: R05 | B42: Open Pipeline by Stage | C42: Detail column | D42: 7 | E42: Close Date | F42: CLOSE_DATE
A43: R05 | B43: Open Pipeline by Stage | C43: Detail column | D43: 8 | E43: Next Step | F43: NEXT_STEP
A44: R05 | B44: Open Pipeline by Stage | C44: Chart X-axis | E44: Stage | F44: STAGE_NAME | G44: Funnel
A45: R06 | B45: Pipeline by Close Quarter (Next 4) | C45: Field filter | E45: Stage | F45: STAGE_NAME | G45: not equal to Deferred,Old / Archived
A46: R06 | B46: Pipeline by Close Quarter (Next 4) | C46: Date filter | E46: Close Date | F46: CLOSE_DATE | G46: Current FQ + Next 3 FQ
A47: R06 | B47: Pipeline by Close Quarter (Next 4) | C47: Group rows by | D47: 1 | E47: Close Date | F47: CLOSE_DATE | G47: Fiscal Quarter | H47: Asc
A48: R06 | B48: Pipeline by Close Quarter (Next 4) | C48: Group columns by | D48: 1 | E48: Forecast Category | F48: FORECAST_CATEGORY | H48: Asc
A49: R06 | B49: Pipeline by Close Quarter (Next 4) | C49: Detail column | D49: 1 | E49: Amount | F49: AMOUNT | G49: Sum
A50: R06 | B50: Pipeline by Close Quarter (Next 4) | C50: Chart X-axis | E50: Close Date | F50: CLOSE_DATE | G50: VerticalColumnStacked
A51: R06 | B51: Pipeline by Close Quarter (Next 4) | C51: Chart series | E51: Forecast Category | F51: FORECAST_CATEGORY | G51: VerticalColumnStacked
A52: R07 | B52: Pipeline by Salesperson & Stage | C52: Field filter | E52: Stage | F52: STAGE_NAME | G52: not equal to Deferred,Old / Archived
A53: R07 | B53: Pipeline by Salesperson & Stage | C53: Date filter | E53: Close Date | F53: CLOSE_DATE | G53: All Time
A54: R07 | B54: Pipeline by Salesperson & Stage | C54: Group rows by | D54: 1 | E54: Opportunity Owner | F54: FULL_NAME | H54: Asc
A55: R07 | B55: Pipeline by Salesperson & Stage | C55: Group columns by | D55: 1 | E55: Stage | F55: STAGE_NAME | H55: Asc
A56: R07 | B56: Pipeline by Salesperson & Stage | C56: Detail column | D56: 1 | E56: Amount | F56: AMOUNT | G56: Sum
A57: R07 | B57: Pipeline by Salesperson & Stage | C57: Chart X-axis | E57: Opportunity Owner | F57: FULL_NAME | G57: HorizontalBarStacked
A58: R07 | B58: Pipeline by Salesperson & Stage | C58: Chart series | E58: Stage | F58: STAGE_NAME | G58: HorizontalBarStacked
A59: R08 | B59: Revenue Won by Salesperson – YTD | C59: Field filter | E59: Stage | F59: STAGE_NAME | G59: equals Closed Won
A60: R08 | B60: Revenue Won by Salesperson – YTD | C60: Date filter | E60: Close Date | F60: CLOSE_DATE | G60: Current FY
A61: R08 | B61: Revenue Won by Salesperson – YTD | C61: Group rows by | D61: 1 | E61: Opportunity Owner | F61: FULL_NAME | H61: Aggregate Amount Desc
A62: R08 | B62: Revenue Won by Salesperson – YTD | C62: Detail column | D62: 1 | E62: Opportunity Name | F62: OPPORTUNITY_NAME
A63: R08 | B63: Revenue Won by Salesperson – YTD | C63: Detail column | D63: 2 | E63: Account Name | F63: ACCOUNT_NAME
A64: R08 | B64: Revenue Won by Salesperson – YTD | C64: Detail column | D64: 3 | E64: Amount | F64: AMOUNT | G64: Sum
A65: R08 | B65: Revenue Won by Salesperson – YTD | C65: Detail column | D65: 4 | E65: Close Date | F65: CLOSE_DATE
A66: R08 | B66: Revenue Won by Salesperson – YTD | C66: Chart X-axis | E66: Opportunity Owner | F66: FULL_NAME | G66: HorizontalBar
A67: R09 | B67: Win Rate by Salesperson – YTD | C67: Date filter | E67: Close Date | F67: CLOSE_DATE | G67: Current FY
A68: R09 | B68: Win Rate by Salesperson – YTD | C68: Group rows by | D68: 1 | E68: Opportunity Owner | F68: FULL_NAME | H68: Asc
A69: R09 | B69: Win Rate by Salesperson – YTD | C69: Detail column | D69: 1 | E69: Opportunity Name | F69: OPPORTUNITY_NAME
A70: R09 | B70: Win Rate by Salesperson – YTD | C70: Detail column | D70: 2 | E70: Stage | F70: STAGE_NAME
A71: R09 | B71: Win Rate by Salesperson – YTD | C71: Detail column | D71: 3 | E71: Amount | F71: AMOUNT | G71: Sum
A72: R09 | B72: Win Rate by Salesperson – YTD | C72: Detail column | D72: 4 | E72: Won | F72: WON
A73: R09 | B73: Win Rate by Salesperson – YTD | C73: Detail column | D73: 5 | E73: Closed | F73: CLOSED
A74: R09 | B74: Win Rate by Salesperson – YTD | C74: Custom summary formula | E74: Win Rate % | F74: FORMULA1 | G74: WON:SUM / CLOSED:SUM
A75: R10 | B75: Win-Loss Analysis by Reason – YTD | C75: Date filter | E75: Close Date | F75: CLOSE_DATE | G75: Current FY
A76: R10 | B76: Win-Loss Analysis by Reason – YTD | C76: Group rows by | D76: 1 | E76: Stage | F76: STAGE_NAME | H76: Asc
A77: R10 | B77: Win-Loss Analysis by Reason – YTD | C77: Group rows by | D77: 2 | E77: Win/Loss Reason | F77: Opportunity.Win_Loss_Reason__c | H77: Asc
A78: R10 | B78: Win-Loss Analysis by Reason – YTD | C78: Detail column | D78: 1 | E78: Opportunity Name | F78: OPPORTUNITY_NAME
A79: R10 | B79: Win-Loss Analysis by Reason – YTD | C79: Detail column | D79: 2 | E79: Account Name | F79: ACCOUNT_NAME
A80: R10 | B80: Win-Loss Analysis by Reason – YTD | C80: Detail column | D80: 3 | E80: Opportunity Owner | F80: FULL_NAME
A81: R10 | B81: Win-Loss Analysis by Reason – YTD | C81: Detail column | D81: 4 | E81: Amount | F81: AMOUNT | G81: Sum
A82: R10 | B82: Win-Loss Analysis by Reason – YTD | C82: Detail column | D82: 5 | E82: Win/Loss Details | F82: Opportunity.Win_Loss_Details__c
A83: R10 | B83: Win-Loss Analysis by Reason – YTD | C83: Chart X-axis | E83: Stage | F83: STAGE_NAME | G83: HorizontalBarStacked
A84: R10 | B84: Win-Loss Analysis by Reason – YTD | C84: Chart series | E84: Win/Loss Reason | F84: Opportunity.Win_Loss_Reason__c | G84: HorizontalBarStacked
A85: R10a | B85: Why We Win – YTD | C85: Field filter | E85: Stage | F85: STAGE_NAME | G85: equals Closed Won
A86: R10a | B86: Why We Win – YTD | C86: Date filter | E86: Close Date | F86: CLOSE_DATE | G86: Current FY
A87: R10a | B87: Why We Win – YTD | C87: Group rows by | D87: 1 | E87: Win/Loss Reason | F87: Opportunity.Win_Loss_Reason__c | H87: Asc
A88: R10a | B88: Why We Win – YTD | C88: Detail column | D88: 1 | E88: Opportunity Name | F88: OPPORTUNITY_NAME
A89: R10a | B89: Why We Win – YTD | C89: Detail column | D89: 2 | E89: Account Name | F89: ACCOUNT_NAME
A90: R10a | B90: Why We Win – YTD | C90: Detail column | D90: 3 | E90: Opportunity Owner | F90: FULL_NAME
A91: R10a | B91: Why We Win – YTD | C91: Detail column | D91: 4 | E91: Amount | F91: AMOUNT | G91: Sum
A92: R10a | B92: Why We Win – YTD | C92: Detail column | D92: 5 | E92: Win/Loss Details | F92: Opportunity.Win_Loss_Details__c
A93: R10a | B93: Why We Win – YTD | C93: Chart X-axis | E93: Win/Loss Reason | F93: Opportunity.Win_Loss_Reason__c | G93: Donut
A94: R10b | B94: Why We Lose – YTD | C94: Field filter | E94: Stage | F94: STAGE_NAME | G94: equals Closed Lost
A95: R10b | B95: Why We Lose – YTD | C95: Date filter | E95: Close Date | F95: CLOSE_DATE | G95: Current FY
A96: R10b | B96: Why We Lose – YTD | C96: Group rows by | D96: 1 | E96: Win/Loss Reason | F96: Opportunity.Win_Loss_Reason__c | H96: Asc
A97: R10b | B97: Why We Lose – YTD | C97: Detail column | D97: 1 | E97: Opportunity Name | F97: OPPORTUNITY_NAME
A98: R10b | B98: Why We Lose – YTD | C98: Detail column | D98: 2 | E98: Account Name | F98: ACCOUNT_NAME
A99: R10b | B99: Why We Lose – YTD | C99: Detail column | D99: 3 | E99: Opportunity Owner | F99: FULL_NAME
A100: R10b | B100: Why We Lose – YTD | C100: Detail column | D100: 4 | E100: Amount | F100: AMOUNT | G100: Sum
...

Sheet Field Usage Matrix
A1: Field | B1: Field API name | C1: R01 | D1: R02 | E1: R03 | F1: R04 | G1: R05 | H1: R06 | I1: R07 | J1: R08 | K1: R09 | L1: R10 | M1: R10a | N1: R10b | O1: R11 | P1: R12 | Q1: R13 | R1: R14 | S1: R15 | T1: R16 | U1: R17 | V1: R18 | W1: Reports using it
A2: Account Name | B2: ACCOUNT_NAME | C2: C | D2: C | E2: C | G2: C | J2: C | L2: C | M2: C | N2: C | O2: C | Q2: C | S2: C | U2: C | W2: =COUNTIF(C2:V2,"?*") -> 12
A3: Account: Billing Country | B3: ADDRESS1_COUNTRY_CODE | T3: GC | W3: =COUNTIF(C3:V3,"?*") -> 1
A4: Account: Industry | B4: INDUSTRY | T4: GR | W4: =COUNTIF(C4:V4,"?*") -> 1
A5: Account: Segment | B5: Account.Segment__c | T5: C | W5: =COUNTIF(C5:V5,"?*") -> 1
A6: Age | B6: AGE | V6: CΣ | W6: =COUNTIF(C6:V6,"?*") -> 1
A7: Amount | B7: AMOUNT | C7: CΣ | D7: CΣ | E7: CΣ | F7: CΣ | G7: CΣ | H7: CΣ | I7: CΣ | J7: CΣ | K7: CΣ | L7: CΣ | M7: CΣ | N7: CΣ | O7: CΣ | P7: CΣ S | Q7: CΣ | R7: CΣ | S7: CΣ | T7: CΣ | U7: CΣ | V7: CΣ | W7: =COUNTIF(C7:V7,"?*") -> 20
A8: Close Date | B8: CLOSE_DATE | C8: D GR | D8: D C | E8: D C | F8: D GC | G8: D C | H8: D GR | I8: D | J8: D C | K8: D | L8: D | M8: D | N8: D | O8: D C S | P8: F D C | Q8: D C | R8: D | S8: D | T8: D | V8: F D C | W8: =COUNTIF(C8:V8,"?*") -> 19
A9: Close Month | B9: CLOSE_MONTH | C9: GR | W9: =COUNTIF(C9:V9,"?*") -> 1
A10: Close Quarter | B10: Opportunity.Close_Quarter__c | F10: GR | W10: =COUNTIF(C10:V10,"?*") -> 1
A11: Closed | B11: CLOSED | K11: C | W11: =COUNTIF(C11:V11,"?*") -> 1
A12: Created Date | B12: CREATED_DATE | V12: C | W12: =COUNTIF(C12:V12,"?*") -> 1
A13: Deferred Date | B13: Opportunity.Deferred_Date__c | Q13: C | W13: =COUNTIF(C13:V13,"?*") -> 1
A14: Expected Revenue | B14: EXP_AMOUNT | G14: CΣ | W14: =COUNTIF(C14:V14,"?*") -> 1
A15: Forecast Category | B15: FORECAST_CATEGORY | H15: GC | W15: =COUNTIF(C15:V15,"?*") -> 1
A16: Last Activity | B16: LAST_ACTIVITY | P16: F C | W16: =COUNTIF(C16:V16,"?*") -> 1
A17: Last Modified Date | B17: LAST_UPDATE | P17: C | W17: =COUNTIF(C17:V17,"?*") -> 1
A18: Lead Source | B18: LEAD_SOURCE | S18: GR | W18: =COUNTIF(C18:V18,"?*") -> 1
A19: Next Step | B19: NEXT_STEP | G19: C | O19: C | W19: =COUNTIF(C19:V19,"?*") -> 2
A20: Opportunity Name | B20: OPPORTUNITY_NAME | C20: C | D20: C | E20: C | G20: C | J20: C | K20: C | L20: C | M20: C | N20: C | O20: C | P20: C | Q20: C | S20: C | U20: C | V20: C | W20: =COUNTIF(C20:V20,"?*") -> 15
A21: Opportunity Owner | B21: FULL_NAME | C21: C | D21: GR | E21: GR | G21: C | I21: GR | J21: GR | K21: GR | L21: C | M21: C | N21: C | O21: C | P21: C | Q21: GR | U21: C | V21: GR | W21: =COUNTIF(C21:V21,"?*") -> 15
A22: Primary Campaign Source | B22: CAMPAIGN_SOURCE | S22: GR | W22: =COUNTIF(C22:V22,"?*") -> 1
A23: Probability (%) | B23: PROBABILITY | G23: C | W23: =COUNTIF(C23:V23,"?*") -> 1
A24: Proposal Submission Date | B24: Opportunity.Proposal_Submission_Date__c | U24: D C S | W24: =COUNTIF(C24:V24,"?*") -> 1
A25: Stage | B25: STAGE_NAME | C25: F | D25: F | E25: F | F25: F | G25: F GR | H25: F | I25: F GC | J25: F | K25: C | L25: GR | M25: F | N25: F | O25: F C | P25: F C | Q25: F | R25: F | S25: F | T25: F | U25: C | V25: F | W25: =COUNTIF(C25:V25,"?*") -> 20
A26: Type | B26: TYPE | C26: C | R26: GR | W26: =COUNTIF(C26:V26,"?*") -> 2
A27: Win Rate % (custom summary formula) | B27: FORMULA1 | K27: SF | W27: =COUNTIF(C27:V27,"?*") -> 1
A28: Win/Loss Details | B28: Opportunity.Win_Loss_Details__c | L28: C | M28: C | N28: C | Q28: C | W28: =COUNTIF(C28:V28,"?*") -> 4
A29: Win/Loss Reason | B29: Opportunity.Win_Loss_Reason__c | L29: GR | M29: GR | N29: GR | W29: =COUNTIF(C29:V29,"?*") -> 3
A30: Won | B30: WON | K30: C | R30: GC | W30: =COUNTIF(C30:V30,"?*") -> 2
A32: Legend | B32: F = field filter · D = date-range filter · GR = group rows · GC = group columns · C = detail column · CΣ = column with summary · SF = custom summary formula · S = report sort

Sheet Dashboards
A1: Dashboard ID | B1: Title | C1: API name | D1: Folder | E1: Description | F1: Dashboard type | G1: Running user (View as) | H1: Grid columns | I1: Row height (px) | J1: Components | K1: Theme / palette | L1: Dashboard filter | M1: Filter field | N1: Filter options (operator: equals) | O1: Shown on Home page
A2: D1 | B2: ABA Management – Revenue & Pipeline | C2: ABA_Management_Revenue_Pipeline | D2: ABA Management Dashboards | E2: D1: revenue won (MTD/QTD/YTD), year-on-year trend, pipeline and deals to push now. | F2: Run as a specified user | G2: suraj.od.885d11d47e1b@agentforce.com | H2: 12 | I2: 36 | J2: 9 | K2: light / unity | L2: Opportunity Owner | M2: Opportunity Owner (FULL_NAME) | N2: All, Mohammed Alburayh, Suraj OD, Venkatesh Rethinasamy | O2: Yes – top region
A3: D1 | B3: ABA Management – Revenue & Pipeline | C3: ABA_Management_Revenue_Pipeline | D3: ABA Management Dashboards | F3: Run as a specified user | G3: suraj.od.885d11d47e1b@agentforce.com | H3: 12 | I3: 36 | J3: 9 | K3: light / unity | L3: Account Industry | M3: Account: Industry (INDUSTRY) | N3: All, Agriculture, Banking, Construction, Education, Energy, Food & Beverage, Healthcare, Manufacturing, Oil & Gas, Retail, Telecommunications, Transportation | O3: Yes – top region
A4: D2 | B4: ABA Sales Performance & Win-Loss | C4: ABA_Sales_Performance_Win_Loss | D4: ABA Management Dashboards | E4: D2: salesperson leaderboard, pipeline coverage, win rate, win/loss reasons, revenue mix and hygiene. | F4: Run as a specified user | G4: suraj.od.885d11d47e1b@agentforce.com | H4: 12 | I4: 36 | J4: 9 | K4: light / unity | L4: Opportunity Owner | M4: Opportunity Owner (FULL_NAME) | N4: All, Mohammed Alburayh, Suraj OD, Venkatesh Rethinasamy | O4: Yes – top region
A5: D2 | B5: ABA Sales Performance & Win-Loss | C5: ABA_Sales_Performance_Win_Loss | D5: ABA Management Dashboards | F5: Run as a specified user | G5: suraj.od.885d11d47e1b@agentforce.com | H5: 12 | I5: 36 | J5: 9 | K5: light / unity | L5: Account Industry | M5: Account: Industry (INDUSTRY) | N5: All, Agriculture, Banking, Construction, Education, Energy, Food & Beverage, Healthcare, Manufacturing, Oil & Gas, Retail, Telecommunications, Transportation | O5: Yes – top region

Sheet Dashboard Components
A1: Dashboard ID | B1: Dashboard | C1: Component # | D1: Header | E1: Component type | F1: Grid row | G1: Grid column | H1: Row span | I1: Column span | J1: Source report ID | K1: Source report | L1: Source report filters | M1: Measure | N1: Groupings (X-axis → series) | O1: Sort | P1: Legend / labels | Q1: Gauge or metric bands | R1: Table columns | S1: Table sort | T1: Responds to dashboard filters | U1: Drill-down | V1: Current value (formula)
A2: D1 | B2: ABA Management – Revenue & Pipeline | C2: 1 | D2: Revenue Won – MTD | E2: Metric | F2: 0 | G2: 0 | H2: 4 | I2: 2 | J2: R02 | K2: Revenue Won – This Month (MTD) | L2: All Opportunities Close Date = Current Calendar Month Stage equals "Closed Won" | M2: Sum of Amount | N2: – | O2: – | P2: label 'Month to date' | Q2: Red below 1,000,000, amber to 1,500,000, green above | R2: – | S2: – | T2: Opportunity Owner, Account: Industry | U2: Off (opens report via View Report) | V2: ='Report Results'!D3 -> 2750000
A3: D1 | B3: ABA Management – Revenue & Pipeline | C3: 2 | D3: Revenue Won – QTD vs Target | E3: Gauge | F3: 0 | G3: 2 | H3: 4 | I3: 3 | J3: R03 | K3: Revenue Won – This Quarter (QTD) | L3: All Opportunities Close Date = Current FQ Stage equals "Closed Won" | M3: Sum of Amount | N3: – | O3: – | P3: percent false | Q3: 0 – 3,000,000 red · 3,000,000 – 4,500,000 amber · 4,500,000 – 5,000,000 green (target 5,000,000) | R3: – | S3: – | T3: Opportunity Owner, Account: Industry | U3: Off (opens report via View Report) | V3: ='Report Results'!D4 -> 2750000
A4: D1 | B4: ABA Management – Revenue & Pipeline | C4: 3 | D4: Revenue Won – YTD | E4: Metric | F4: 0 | G4: 5 | H4: 4 | I4: 3 | J4: R01 | K4: Revenue Won – YTD by Quarter & Month | L4: All Opportunities Close Date = Current FY Stage equals "Closed Won" | M4: Sum of Amount | N4: – | O4: – | P4: label 'Year to date' | Q4: Single neutral colour (no target) | R4: – | S4: – | T4: Opportunity Owner, Account: Industry | U4: Off (opens report via View Report) | V4: ='Report Results'!D2 -> 8900000
A5: D1 | B5: ABA Management – Revenue & Pipeline | C5: 4 | D5: Open Pipeline Value | E5: Metric | F5: 0 | G5: 8 | H5: 4 | I5: 2 | J5: R05 | K5: Open Pipeline by Stage | L5: Open Opportunities Close Date = All Time Stage not equal to "Deferred,Old / Archived" | M5: Sum of Amount | N5: – | O5: – | P5: label 'Active pipeline' | Q5: Single neutral colour (no target) | R5: – | S5: – | T5: Opportunity Owner, Account: Industry | U5: Off (opens report via View Report) | V5: ='Report Results'!D6 -> 31421000
A6: D1 | B6: ABA Management – Revenue & Pipeline | C6: 5 | D6: Win Rate YTD | E6: Metric | F6: 0 | G6: 10 | H6: 4 | I6: 2 | J6: R09 | K6: Win Rate by Salesperson – YTD | L6: Closed Opportunities Close Date = Current FY | M6: Win Rate % (custom summary formula) | N6: – | O6: – | P6: label 'Won / closed' | Q6: Single neutral colour (no target) | R6: – | S6: – | T6: Opportunity Owner, Account: Industry | U6: Off (opens report via View Report) | V6: ='Report Results'!H10 -> 0.6
A7: D1 | B7: ABA Management – Revenue & Pipeline | C7: 6 | D7: Revenue by Quarter – This Year vs Last Year | E7: ColumnGrouped | F7: 4 | G7: 0 | H7: 8 | I7: 6 | J7: R04 | K7: Revenue Won – This Year vs Last Year | L7: All Opportunities Close Date = Previous FY + Current FY Stage equals "Closed Won" | M7: Sum of Amount | N7: Close Quarter → Close Date | O7: RowLabelAscending | P7: legend Bottom, values true, total false, percent false | Q7: – | R7: – | S7: – | T7: Opportunity Owner, Account: Industry | U7: Off (opens report via View Report) | V7: ='Report Results'!D5 -> 16170000
A8: D1 | B8: ABA Management – Revenue & Pipeline | C8: 7 | D8: Pipeline by Stage | E8: Funnel | F8: 4 | G8: 6 | H8: 8 | I8: 6 | J8: R05 | K8: Open Pipeline by Stage | L8: Open Opportunities Close Date = All Time Stage not equal to "Deferred,Old / Archived" | M8: Sum of Amount | N8: Stage | O8: RowLabelAscending | P8: legend Right, values true, total false, percent false | Q8: – | R8: – | S8: – | T8: Opportunity Owner, Account: Industry | U8: Off (opens report via View Report) | V8: ='Report Results'!D6 -> 31421000
A9: D1 | B9: ABA Management – Revenue & Pipeline | C9: 8 | D9: Pipeline by Close Quarter | E9: ColumnStacked | F9: 12 | G9: 0 | H9: 8 | I9: 6 | J9: R06 | K9: Pipeline by Close Quarter (Next 4) | L9: Open Opportunities Close Date = Current FQ + Next 3 FQ Stage not equal to "Deferred,Old / Archived" | M9: Sum of Amount | N9: Close Date → Forecast Category | O9: RowLabelAscending | P9: legend Bottom, values true, total false, percent false | Q9: – | R9: – | S9: – | T9: Opportunity Owner, Account: Industry | U9: Off (opens report via View Report) | V9: ='Report Results'!D7 -> 30271000
A10: D1 | B10: ABA Management – Revenue & Pipeline | C10: 9 | D10: Top Deals Closing in 30 Days | E10: FlexTable | F10: 12 | G10: 6 | H10: 8 | I10: 6 | J10: R11 | K10: Closing in Next 30 Days | L10: Open Opportunities Close Date = Next 30 Days Stage equals "Proposal Submitted,Negotiation,Verbal Award" | M10: Table columns (see right) | N10: – | O10: – | P10: – | Q10: – | R10: Opportunity Name (detail), Account Name (detail), Opportunity Owner (detail), Stage (detail), Amount (detail), Close Date (detail) | S10: Close Date ascending | T10: Opportunity Owner, Account: Industry | U10: Off (opens report via View Report) | V10: ='Report Results'!C14&" rows" -> 3 rows
A11: D2 | B11: ABA Sales Performance & Win-Loss | C11: 1 | D11: Revenue Won by Salesperson | E11: Bar | F11: 0 | G11: 0 | H11: 8 | I11: 4 | J11: R08 | K11: Revenue Won by Salesperson – YTD | L11: All Opportunities Close Date = Current FY Stage equals "Closed Won" | M11: Sum of Amount | N11: Opportunity Owner | O11: RowValueDescending | P11: legend Bottom, values true, total false, percent false | Q11: – | R11: – | S11: – | T11: Opportunity Owner, Account: Industry | U11: Off (opens report via View Report) | V11: ='Report Results'!D9 -> 8900000
A12: D2 | B12: ABA Sales Performance & Win-Loss | C12: 2 | D12: Pipeline by Salesperson & Stage | E12: BarStacked | F12: 0 | G12: 4 | H12: 8 | I12: 4 | J12: R07 | K12: Pipeline by Salesperson & Stage | L12: Open Opportunities Close Date = All Time Stage not equal to "Deferred,Old / Archived" | M12: Sum of Amount | N12: Opportunity Owner → Stage | O12: RowLabelAscending | P12: legend Bottom, values true, total false, percent false | Q12: – | R12: – | S12: – | T12: Opportunity Owner, Account: Industry | U12: Off (opens report via View Report) | V12: ='Report Results'!D8 -> 31421000
A13: D2 | B13: ABA Sales Performance & Win-Loss | C13: 3 | D13: Win Rate by Salesperson | E13: FlexTable | F13: 0 | G13: 8 | H13: 8 | I13: 4 | J13: R09 | K13: Win Rate by Salesperson – YTD | L13: Closed Opportunities Close Date = Current FY | M13: Table columns (see right) | N13: – | O13: – | P13: – | Q13: – | R13: Opportunity Owner (grouping), Win Rate % (custom summary formula) (aggregate), Record Count (aggregate) | S13: Win Rate % (custom summary formula) descending | T13: Opportunity Owner, Account: Industry | U13: Off (opens report via View Report) | V13: ='Report Results'!C10&" rows" -> 15 rows
A14: D2 | B14: ABA Sales Performance & Win-Loss | C14: 4 | D14: Why We Win | E14: Donut | F14: 8 | G14: 0 | H14: 8 | I14: 4 | J14: R10a | K14: Why We Win – YTD | L14: All Opportunities Close Date = Current FY Stage equals "Closed Won" | M14: Sum of Amount | N14: Win/Loss Reason | O14: RowLabelAscending | P14: legend Right, values true, total true, percent false | Q14: – | R14: – | S14: – | T14: Opportunity Owner, Account: Industry | U14: Off (opens report via View Report) | V14: ='Report Results'!D12 -> 8900000
A15: D2 | B15: ABA Sales Performance & Win-Loss | C15: 5 | D15: Why We Lose | E15: Donut | F15: 8 | G15: 4 | H15: 8 | I15: 4 | J15: R10b | K15: Why We Lose – YTD | L15: All Opportunities Close Date = Current FY Stage equals "Closed Lost" | M15: Sum of Amount | N15: Win/Loss Reason | O15: RowLabelAscending | P15: legend Right, values true, total true, percent false | Q15: – | R15: – | S15: – | T15: Opportunity Owner, Account: Industry | U15: Off (opens report via View Report) | V15: ='Report Results'!D13 -> 5820000
A16: D2 | B16: ABA Sales Performance & Win-Loss | C16: 6 | D16: Revenue by Type (New vs Existing) | E16: Donut | F16: 8 | G16: 8 | H16: 8 | I16: 4 | J16: R14 | K16: Revenue & Pipeline by Type | L16: All Opportunities Close Date = Current FY Stage not equal to "Closed Lost,Deferred,Old / Archived" | M16: Sum of Amount | N16: Type | O16: RowLabelAscending | P16: legend Right, values true, total true, percent false | Q16: – | R16: – | S16: – | T16: Opportunity Owner, Account: Industry | U16: Off (opens report via View Report) | V16: ='Report Results'!D17 -> 29821000
A17: D2 | B17: ABA Sales Performance & Win-Loss | C17: 7 | D17: Revenue by Lead Source | E17: Bar | F17: 16 | G17: 0 | H17: 8 | I17: 4 | J17: R15 | K17: Revenue by Lead Source & Campaign | L17: All Opportunities Close Date = Current FY Stage equals "Closed Won" | M17: Sum of Amount | N17: Lead Source | O17: RowValueDescending | P17: legend Bottom, values true, total false, percent false | Q17: – | R17: – | S17: – | T17: Opportunity Owner, Account: Industry | U17: Off (opens report via View Report) | V17: ='Report Results'!D18 -> 8900000
A18: D2 | B18: ABA Sales Performance & Win-Loss | C18: 8 | D18: Deferred Value | E18: Metric | F18: 16 | G18: 4 | H18: 8 | I18: 4 | J18: R13 | K18: Deferred Opportunities | L18: All Opportunities Close Date = All Time Stage equals "Deferred" | M18: Sum of Amount | N18: – | O18: – | P18: label 'Revenue on hold' | Q18: Single neutral colour (no target) | R18: – | S18: – | T18: Opportunity Owner, Account: Industry | U18: Off (opens report via View Report) | V18: ='Report Results'!D16 -> 11500000
A19: D2 | B19: ABA Sales Performance & Win-Loss | C19: 9 | D19: Overdue & Stale Deals | E19: FlexTable | F19: 16 | G19: 8 | H19: 8 | I19: 4 | J19: R12 | K19: Overdue & Stale Opportunities | L19: Open Opportunities Close Date = All Time Stage not equal to "Deferred,Old / Archived" Close Date less than "TODAY" Last Activity less than "LAST_N_DAYS:30" | M19: Table columns (see right) | N19: – | O19: – | P19: – | Q19: – | R19: Opportunity Name (detail), Opportunity Owner (detail), Stage (detail), Amount (detail), Close Date (detail) | S19: Amount descending | T19: Opportunity Owner, Account: Industry | U19: Off (opens report via View Report) | V19: ='Report Results'!C15&" rows" -> 2 rows

Sheet Home Page
A1: Lightning page | B1: Template | C1: Assigned to | D1: Region | E1: Position | F1: Component | G1: Shows | H1: Settings
A2: ABA Sales Home Page (ABA_Sales_Home_Page) | B2: home:desktopTemplate | C2: Sales app (standard__LightningSales), desktop Home tab | D2: top | E2: 1 | F2: desktopDashboards:embeddedDashboard | G2: Embedded dashboard: D1 – ABA Management – Revenue & Pipeline | H2: Height 900 px; hide on error false
A3: ABA Sales Home Page (ABA_Sales_Home_Page) | B3: home:desktopTemplate | C3: Sales app (standard__LightningSales), desktop Home tab | D3: top | E3: 2 | F3: desktopDashboards:embeddedDashboard | G3: Embedded dashboard: D2 – ABA Sales Performance & Win-Loss | H3: Height 1050 px; hide on error false
A4: ABA Sales Home Page (ABA_Sales_Home_Page) | B4: home:desktopTemplate | C4: Sales app (standard__LightningSales), desktop Home tab | D4: bottomLeft | E4: 1 | F4: flexipage:reportChart | G4: Report chart: R05 Open Pipeline by Stage | H4: Label 'Open Pipeline by Stage'; cache 1440 min; refresh button true
A5: ABA Sales Home Page (ABA_Sales_Home_Page) | B5: home:desktopTemplate | C5: Sales app (standard__LightningSales), desktop Home tab | D5: bottomRight | E5: 1 | F5: flexipage:reportChart | G5: Report chart: R10a Why We Win – YTD | H5: Label 'Why We Win – YTD'; cache 1440 min; refresh button true
A6: ABA Sales Home Page (ABA_Sales_Home_Page) | B6: home:desktopTemplate | C6: Sales app (standard__LightningSales), desktop Home tab | D6: sidebar | E6: 1 | F6: flexipage:reportChart | G6: Report chart: R08 Revenue Won by Salesperson – YTD | H6: Label 'Revenue Won by Salesperson – YTD'; cache 1440 min; refresh button true
A7: ABA Sales Home Page (ABA_Sales_Home_Page) | B7: home:desktopTemplate | C7: Sales app (standard__LightningSales), desktop Home tab | D7: sidebar | E7: 2 | F7: flexipage:reportChart | G7: Report chart: R01 Revenue Won – YTD by Quarter & Month | H7: Label 'Revenue Won – YTD'; cache 1440 min; refresh button true

Sheet Opportunity Data
A1: Opportunity ID | B1: Opportunity Name | C1: Account Name | D1: Account: Industry | E1: Account: Billing Country | F1: Account: Segment | G1: Opportunity Owner | H1: Stage | I1: Closed | J1: Won | K1: Probability (%) | L1: Amount | M1: Expected Revenue | N1: Close Date | O1: Close Quarter | P1: Fiscal Year | Q1: Forecast Category | R1: Type | S1: Lead Source | T1: Primary Campaign Source | U1: Offering | V1: Proposal Submission Date | W1: Win/Loss Reason | X1: Win/Loss Details | Y1: Deferred Date | Z1: Next Step | AA1: Last Activity | AB1: Created Date | AC1: Age (days) | AD1: Source of record | AE1: In R01 | AF1: In R02 | AG1: In R03 | AH1: In R04 | AI1: In R05 | AJ1: In R06 | AK1: In R07 | AL1: In R08 | AM1: In R09 | AN1: In R10 | AO1: In R10a | AP1: In R10b | AQ1: In R11 | AR1: In R12 | AS1: In R13 | AT1: In R14 | AU1: In R15 | AV1: In R16 | AW1: In R17 | AX1: In R18
A2: 006gK00000Po2EjQAJ | B2: Desert Bloom Foods – SAP SuccessFactors 2025 | C2: Desert Bloom Foods | D2: Food & Beverage | E2: Saudi Arabia | F2: SME | G2: Suraj OD | H2: Closed Won | I2: 1 | J2: 1 | K2: 1 | L2: 900000 | M2: =L2*K2 -> 900000 | N2: 45711 | O2: Q1 | P2: 2025 | Q2: Closed | R2: Existing Customer – New Opportunity | S2: Web | U2: SAP SuccessFactors | V2: 45680 | W2: Partner (SAP) Influence | X2: Won: partner (sap) influence | AB2: 45650 | AC2: =IF(I2=1,N2-AB2,Overview!$B$5-AB2) -> 61 | AD2: ABA sample CSV | AE2: 0 | AF2: 0 | AG2: 0 | AH2: 1 | AI2: 0 | AJ2: 0 | AK2: 0 | AL2: 0 | AM2: 0 | AN2: 0 | AO2: 0 | AP2: 0 | AQ2: 0 | AR2: 0 | AS2: 0 | AT2: 0 | AU2: 0 | AV2: 0 | AW2: 0 | AX2: 0
A3: 006gK00000Po2EoQAJ | B3: Qassim Agri Ventures – SAP S/4HANA 2025 | C3: Qassim Agri Ventures | D3: Agriculture | E3: Saudi Arabia | F3: SME | G3: Suraj OD | H3: Closed Lost | I3: 1 | J3: 0 | K3: 0 | L3: 2200000 | M3: =L3*K3 -> 0 | N3: 45723 | O3: Q1 | P3: 2025 | Q3: Omitted | R3: Existing Customer – Support | S3: SAP Leads | U3: SAP S/4HANA | V3: 45664 | W3: Budget Cut / No Decision | X3: Lost: budget cut / no decision | AB3: 45599 | AC3: =IF(I3=1,N3-AB3,Overview!$B$5-AB3) -> 124 | AD3: ABA sample CSV | AE3: 0 | AF3: 0 | AG3: 0 | AH3: 0 | AI3: 0 | AJ3: 0 | AK3: 0 | AL3: 0 | AM3: 0 | AN3: 0 | AO3: 0 | AP3: 0 | AQ3: 0 | AR3: 0 | AS3: 0 | AT3: 0 | AU3: 0 | AV3: 0 | AW3: 0 | AX3: 0
A4: 006gK00000Po2F0QAJ | B4: Riyadh Smart Utilities – SAP S/4HANA 2025 | C4: Riyadh Smart Utilities | D4: Energy | E4: Saudi Arabia | F4: Enterprise | G4: Venkatesh Rethinasamy | H4: Closed Lost | I4: 1 | J4: 0 | K4: 0 | L4: 450000 | M4: =L4*K4 -> 0 | N4: 45730 | O4: Q1 | P4: 2025 | Q4: Omitted | R4: Existing Customer – Support | S4: Events & Campaigns | U4: SAP S/4HANA | V4: 45695 | W4: Budget Cut / No Decision | X4: Lost: budget cut / no decision | AB4: 45636 | AC4: =IF(I4=1,N4-AB4,Overview!$B$5-AB4) -> 94 | AD4: ABA sample CSV | AE4: 0 | AF4: 0 | AG4: 0 | AH4: 0 | AI4: 0 | AJ4: 0 | AK4: 0 | AL4: 0 | AM4: 0 | AN4: 0 | AO4: 0 | AP4: 0 | AQ4: 0 | AR4: 0 | AS4: 0 | AT4: 0 | AU4: 0 | AV4: 0 | AW4: 0 | AX4: 0
A5: 006gK00000Po2EkQAJ | B5: Taiba Education Co – SAP SuccessFactors 2025 | C5: Taiba Education Co | D5: Education | E5: Saudi Arabia | F5: Corporate | G5: Venkatesh Rethinasamy | H5: Closed Won | I5: 1 | J5: 1 | K5: 1 | L5: 150000 | M5: =L5*K5 -> 150000 | N5: 45750 | O5: Q2 | P5: 2025 | Q5: Closed | R5: Existing Customer – New Opportunity | S5: SAP Leads | U5: SAP SuccessFactors | V5: 45710 | W5: Price Competitiveness | X5: Won: price competitiveness | AB5: 45673 | AC5: =IF(I5=1,N5-AB5,Overview!$B$5-AB5) -> 77 | AD5: ABA sample CSV | AE5: 0 | AF5: 0 | AG5: 0 | AH5: 1 | AI5: 0 | AJ5: 0 | AK5: 0 | AL5: 0 | AM5: 0 | AN5: 0 | AO5: 0 | AP5: 0 | AQ5: 0 | AR5: 0 | AS5: 0 | AT5: 0 | AU5: 0 | AV5: 0 | AW5: 0 | AX5: 0
A6: 006gK00000Po2EyQAJ | B6: Emirates Facility Mgmt – SAP Support (AMS) 2025 | C6: Emirates Facility Mgmt | D6: Construction | E6: United Arab Emirates | F6: Corporate | G6: Venkatesh Rethinasamy | H6: Closed Won | I6: 1 | J6: 1 | K6: 1 | L6: 150000 | M6: =L6*K6 -> 150000 | N6: 45811 | O6: Q2 | P6: 2025 | Q6: Closed | R6: Existing Customer – New Opportunity | S6: Events & Campaigns | U6: SAP Support (AMS) | V6: 45766 | W6: Customer Relationship / Incumbent | X6: Won: customer relationship / incumbent | AB6: 45721 | AC6: =IF(I6=1,N6-AB6,Overview!$B$5-AB6) -> 90 | AD6: ABA sample CSV | AE6: 0 | AF6: 0 | AG6: 0 | AH6: 1 | AI6: 0 | AJ6: 0 | AK6: 0 | AL6: 0 | AM6: 0 | AN6: 0 | AO6: 0 | AP6: 0 | AQ6: 0 | AR6: 0 | AS6: 0 | AT6: 0 | AU6: 0 | AV6: 0 | AW6: 0 | AX6: 0
A7: 006gK00000Po2F2QAJ | B7: Al Noor Healthcare – Data & Analytics 2025 | C7: Al Noor Healthcare | D7: Healthcare | E7: Saudi Arabia | F7: Enterprise | G7: Suraj OD | H7: Closed Lost | I7: 1 | J7: 0 | K7: 0 | L7: 900000 | M7: =L7*K7 -> 0 | N7: 45814 | O7: Q2 | P7: 2025 | Q7: Omitted | R7: Net New Names | S7: Web | U7: Data & Analytics | V7: 45766 | W7: Lost to Competitor | X7: Lost: lost to competitor | AB7: 45693 | AC7: =IF(I7=1,N7-AB7,Overview!$B$5-AB7) -> 121 | AD7: ABA sample CSV | AE7: 0 | AF7: 0 | AG7: 0 | AH7: 0 | AI7: 0 | AJ7: 0 | AK7: 0 | AL7: 0 | AM7: 0 | AN7: 0 | AO7: 0 | AP7: 0 | AQ7: 0 | AR7: 0 | AS7: 0 | AT7: 0 | AU7: 0 | AV7: 0 | AW7: 0 | AX7: 0
A8: 006gK00000Po2ExQAJ | B8: Red Sea Logistics – SAP S/4HANA 2025 | C8: Red Sea Logistics | D8: Transportation | E8: Saudi Arabia | F8: Corporate | G8: Suraj OD | H8: Closed Won | I8: 1 | J8: 1 | K8: 1 | L8: 320000 | M8: =L8*K8 -> 320000 | N8: 45816 | O8: Q2 | P8: 2025 | Q8: Closed | R8: Existing Customer – New Opportunity | S8: Phone Inquiry | U8: SAP S/4HANA | V8: 45791 | W8: Technical Solution Fit | X8: Won: technical solution fit | AB8: 45753 | AC8: =IF(I8=1,N8-AB8,Overview!$B$5-AB8) -> 63 | AD8: ABA sample CSV | AE8: 0 | AF8: 0 | AG8: 0 | AH8: 1 | AI8: 0 | AJ8: 0 | AK8: 0 | AL8: 0 | AM8: 0 | AN8: 0 | AO8: 0 | AP8: 0 | AQ8: 0 | AR8: 0 | AS8: 0 | AT8: 0 | AU8: 0 | AV8: 0 | AW8: 0 | AX8: 0
A9: 006gK00000Po2F4QAJ | B9: Emirates Facility Mgmt – Cloud Migration 2025 | C9: Emirates Facility Mgmt | D9: Construction | E9: United Arab Emirates | F9: Corporate | G9: Suraj OD | H9: Closed Won | I9: 1 | J9: 1 | K9: 1 | L9: 3500000 | M9: =L9*K9 -> 3500000 | N9: 45827 | O9: Q2 | P9: 2025 | Q9: Closed | R9: Existing Customer – Upgrade/Upsell | S9: Sales Outreach | U9: Cloud Migration | V9: 45769 | W9: Technical Solution Fit | X9: Won: technical solution fit | AB9: 45727 | AC9: =IF(I9=1,N9-AB9,Overview!$B$5-AB9) -> 100 | AD9: ABA sample CSV | AE9: 0 | AF9: 0 | AG9: 0 | AH9: 1 | AI9: 0 | AJ9: 0 | AK9: 0 | AL9: 0 | AM9: 0 | AN9: 0 | AO9: 0 | AP9: 0 | AQ9: 0 | AR9: 0 | AS9: 0 | AT9: 0 | AU9: 0 | AV9: 0 | AW9: 0 | AX9: 0
A10: 006gK00000Po2EnQAJ | B10: Oasis Manufacturing – SAP Support (AMS) 2025 | C10: Oasis Manufacturing | D10: Manufacturing | E10: Saudi Arabia | F10: SME | G10: Suraj OD | H10: Closed Won | I10: 1 | J10: 1 | K10: 1 | L10: 1500000 | M10: =L10*K10 -> 1500000 | N10: 45847 | O10: Q3 | P10: 2025 | Q10: Closed | R10: Net New Names | S10: Events & Campaigns | U10: SAP Support (AMS) | V10: 45810 | W10: Partner (SAP) Influence | X10: Won: partner (sap) influence | AB10: 45752 | AC10: =IF(I10=1,N10-AB10,Overview!$B$5-AB10) -> 95 | AD10: ABA sample CSV | AE10: 0 | AF10: 0 | AG10: 0 | AH10: 1 | AI10: 0 | AJ10: 0 | AK10: 0 | AL10: 0 | AM10: 0 | AN10: 0 | AO10: 0 | AP10: 0 | AQ10: 0 | AR10: 0 | AS10: 0 | AT10: 0 | AU10: 0 | AV10: 0 | AW10: 0 | AX10: 0
A11: 006gK00000Po2ElQAJ | B11: Gulf Petrochem Services – Data & Analytics 2025 | C11: Gulf Petrochem Services | D11: Oil & Gas | E11: Saudi Arabia | F11: Enterprise | G11: Mohammed Alburayh | H11: Closed Lost | I11: 1 | J11: 0 | K11: 0 | L11: 250000 | M11: =L11*K11 -> 0 | N11: 45890 | O11: Q3 | P11: 2025 | Q11: Omitted | R11: Existing Customer – New Opportunity | S11: SAP Leads | U11: Data & Analytics | V11: 45862 | W11: Scope Cancelled | X11: Lost: scope cancelled | AB11: 45818 | AC11: =IF(I11=1,N11-AB11,Overview!$B$5-AB11) -> 72 | AD11: ABA sample CSV | AE11: 0 | AF11: 0 | AG11: 0 | AH11: 0 | AI11: 0 | AJ11: 0 | AK11: 0 | AL11: 0 | AM11: 0 | AN11: 0 | AO11: 0 | AP11: 0 | AQ11: 0 | AR11: 0 | AS11: 0 | AT11: 0 | AU11: 0 | AV11: 0 | AW11: 0 | AX11: 0
A12: 006gK00000Po2F5QAJ | B12: Taiba Education Co – SAP S/4HANA 2025 | C12: Taiba Education Co | D12: Education | E12: Saudi Arabia | F12: Corporate | G12: Mohammed Alburayh | H12: Closed Lost | I12: 1 | J12: 0 | K12: 0 | L12: 1500000 | M12: =L12*K12 -> 0 | N12: 45967 | O12: Q4 | P12: 2025 | Q12: Omitted | R12: Existing Customer – Support | S12: Phone Inquiry | U12: SAP S/4HANA | V12: 45926 | W12: Pricing / Commercial | X12: Lost: pricing / commercial | AB12: 45877 | AC12: =IF(I12=1,N12-AB12,Overview!$B$5-AB12) -> 90 | AD12: ABA sample CSV | AE12: 0 | AF12: 0 | AG12: 0 | AH12: 0 | AI12: 0 | AJ12: 0 | AK12: 0 | AL12: 0 | AM12: 0 | AN12: 0 | AO12: 0 | AP12: 0 | AQ12: 0 | AR12: 0 | AS12: 0 | AT12: 0 | AU12: 0 | AV12: 0 | AW12: 0 | AX12: 0
A13: 006gK00000Po2EpQAJ | B13: Oasis Manufacturing – Cloud Migration 2025 | C13: Oasis Manufacturing | D13: Manufacturing | E13: Saudi Arabia | F13: SME | G13: Venkatesh Rethinasamy | H13: Closed Won | I13: 1 | J13: 1 | K13: 1 | L13: 750000 | M13: =L13*K13 -> 750000 | N13: 45968 | O13: Q4 | P13: 2025 | Q13: Closed | R13: Existing Customer – New Opportunity | S13: Partner Referral | U13: Cloud Migration | V13: 45928 | W13: Technical Solution Fit | X13: Won: technical solution fit | AB13: 45856 | AC13: =IF(I13=1,N13-AB13,Overview!$B$5-AB13) -> 112 | AD13: ABA sample CSV | AE13: 0 | AF13: 0 | AG13: 0 | AH13: 1 | AI13: 0 | AJ13: 0 | AK13: 0 | AL13: 0 | AM13: 0 | AN13: 0 | AO13: 0 | AP13: 0 | AQ13: 0 | AR13: 0 | AS13: 0 | AT13: 0 | AU13: 0 | AV13: 0 | AW13: 0 | AX13: 1
... A26: 006gK00000Po2EzQAJ | B26: Bahrain Telecom Partners – SAP S/4HANA 2026 | C26: Bahrain Telecom Partners | D26: Telecommunications | E26: Bahrain | F26: Corporate | G26: Venkatesh Rethinasamy | H26: Closed Won | I26: 1 | J26: 1 | K26: 1 | L26: 1200000 | M26: =L26*K26 -> 1200000 | N26: 46234 | O26: Q3 | P26: 2026 | Q26: Closed | R26: Existing Customer – Change Request | S26: Sales Outreach | U26: SAP S/4HANA | V26: 46184 | W26: Delivery Capability & References | X26: Won: delivery capability & references | AB26: 46132 | AC26: =IF(I26=1,N26-AB26,Overview!$B$5-AB26) -> 102 | AD26: ABA sample CSV | AE26: 1 | AF26: 0 | AG26: 0 | AH26: 1 | AI26: 0 | AJ26: 0 | AK26: 0 | AL26: 1 | AM26: 1 | AN26: 1 | AO26: 1 | AP26: 0 | AQ26: 0 | AR26: 0 | AS26: 0 | AT26: 1 | AU26: 1 | AV26: 1 | AW26: 0 | AX26: 1
A27: 006gK00000Po2FOQAZ | B27: Riyadh Smart Utilities – SAP S/4HANA 2026 | C27: Riyadh Smart Utilities | D27: Energy | E27: Saudi Arabia | F27: Enterprise | G27: Suraj OD | H27: Internal Review | I27: 0 | J27: 0 | K27: 0.5 | L27: 900000 | M27: =L27*K27 -> 450000 | N27: 46239 | O27: Q3 | P27: 2026 | Q27: Pipeline | R27: Net New Names | S27: Phone Inquiry | U27: SAP S/4HANA | V27: 46199 | AB27: 46152 | AC27: =IF(I27=1,N27-AB27,Overview!$B$5-AB27) -> 151 | AD27: ABA sample CSV | AE27: 0 | AF27: 0 | AG27: 0 | AH27: 0 | AI27: 1 | AJ27: 0 | AK27: 1 | AL27: 0 | AM27: 0 | AN27: 0 | AO27: 0 | AP27: 0 | AQ27: 0 | AR27: 1 | AS27: 0 | AT27: 1 | AU27: 0 | AV27: 0 | AW27: 0 | AX27: 0
A28: 006gK00000Po2F1QAJ | B28: Gulf Petrochem Services – SAP S/4HANA 2026 | C28: Gulf Petrochem Services | D28: Oil & Gas | E28: Saudi Arabia | F28: Enterprise | G28: Mohammed Alburayh | H28: Closed Won | I28: 1 | J28: 1 | K28: 1 | L28: 150000 | M28: =L28*K28 -> 150000 | N28: 46242 | O28: Q3 | P28: 2026 | Q28: Closed | R28: Net New Names | S28: Web | U28: SAP S/4HANA | V28: 46194 | W28: Price Competitiveness | X28: Won: price competitiveness | AB28: 46128 | AC28: =IF(I28=1,N28-AB28,Overview!$B$5-AB28) -> 114 | AD28: ABA sample CSV | AE28: 1 | AF28: 0 | AG28: 0 | AH28: 1 | AI28: 0 | AJ28: 0 | AK28: 0 | AL28: 1 | AM28: 1 | AN28: 1 | AO28: 1 | AP28: 0 | AQ28: 0 | AR28: 0 | AS28: 0 | AT28: 1 | AU28: 1 | AV28: 1 | AW28: 0 | AX28: 1
A29: 006gK00000Po2FPQAZ | B29: Bahrain Telecom Partners – SAP Support (AMS) 2026 | C29: Bahrain Telecom Partners | D29: Telecommunications | E29: Bahrain | F29: Corporate | G29: Venkatesh Rethinasamy | H29: Verbal Award | I29: 0 | J29: 0 | K29: 0.9 | L29: 250000 | M29: =L29*K29 -> 225000 | N29: 46295 | O29: Q3 | P29: 2026 | Q29: Commit | R29: Existing Customer – Support | S29: Phone Inquiry | U29: SAP Support (AMS) | V29: 46247 | AB29: 46193 | AC29: =IF(I29=1,N29-AB29,Overview!$B$5-AB29) -> 110 | AD29: ABA sample CSV | AE29: 0 | AF29: 0 | AG29: 0 | AH29: 0 | AI29: 1 | AJ29: 0 | AK29: 1 | AL29: 0 | AM29: 0 | AN29: 0 | AO29: 0 | AP29: 0 | AQ29: 0 | AR29: 1 | AS29: 0 | AT29: 1 | AU29: 0 | AV29: 0 | AW29: 0 | AX29: 0
A30: 006gK00000Po2FVQAZ | B30: Najd Retail Group – SAP S/4HANA 2026 | C30: Najd Retail Group | D30: Retail | E30: Saudi Arabia | F30: Corporate | G30: Venkatesh Rethinasamy | H30: Closed Won | I30: 1 | J30: 1 | K30: 1 | L30: 1800000 | M30: =L30*K30 -> 1800000 | N30: 46297 | O30: Q4 | P30: 2026 | Q30: Closed | R30: Existing Customer – New Opportunity | S30: Sales Outreach | U30: SAP S/4HANA | V30: 46267 | W30: Price Competitiveness | X30: Won: price competitiveness | AB30: 46216 | AC30: =IF(I30=1,N30-AB30,Overview!$B$5-AB30) -> 81 | AD30: ABA sample CSV | AE30: 1 | AF30: 1 | AG30: 1 | AH30: 1 | AI30: 0 | AJ30: 0 | AK30: 0 | AL30: 1 | AM30: 1 | AN30: 1 | AO30: 1 | AP30: 0 | AQ30: 0 | AR30: 0 | AS30: 0 | AT30: 1 | AU30: 1 | AV30: 1 | AW30: 0 | AX30: 1
A31: 006gK00000Po2FWQAZ | B31: Al Noor Healthcare – SAP SuccessFactors 2026 | C31: Al Noor Healthcare | D31: Healthcare | E31: Saudi Arabia | F31: Enterprise | G31: Suraj OD | H31: Closed Won | I31: 1 | J31: 1 | K31: 1 | L31: 950000 | M31: =L31*K31 -> 950000 | N31: 46301 | O31: Q4 | P31: 2026 | Q31: Closed | R31: Existing Customer – New Opportunity | S31: Sales Outreach | U31: SAP SuccessFactors | V31: 46271 | W31: Technical Solution Fit | X31: Won: technical solution fit | AB31: 46213 | AC31: =IF(I31=1,N31-AB31,Overview!$B$5-AB31) -> 88 | AD31: ABA sample CSV | AE31: 1 | AF31: 1 | AG31: 1 | AH31: 1 | AI31: 0 | AJ31: 0 | AK31: 0 | AL31: 1 | AM31: 1 | AN31: 1 | AO31: 1 | AP31: 0 | AQ31: 0 | AR31: 0 | AS31: 0 | AT31: 1 | AU31: 1 | AV31: 1 | AW31: 0 | AX31: 1
A32: 006gK00000Po2FYQAZ | B32: Khaleej Finance House – Cloud Migration 2026 | C32: Khaleej Finance House | D32: Banking | E32: United Arab Emirates | F32: Enterprise | G32: Venkatesh Rethinasamy | H32: Verbal Award | I32: 0 | J32: 0 | K32: 0.9 | L32: 1300000 | M32: =L32*K32 -> 1170000 | N32: 46315 | O32: Q4 | P32: 2026 | Q32: Commit | R32: Existing Customer – New Opportunity | S32: Sales Outreach | U32: Cloud Migration | V32: 46285 | AB32: 46213 | AC32: =IF(I32=1,N32-AB32,Overview!$B$5-AB32) -> 90 | AD32: ABA sample CSV | AE32: 0 | AF32: 0 | AG32: 0 | AH32: 0 | AI32: 1 | AJ32: 1 | AK32: 1 | AL32: 0 | AM32: 0 | AN32: 0 | AO32: 0 | AP32: 0 | AQ32: 1 | AR32: 0 | AS32: 0 | AT32: 1 | AU32: 0 | AV32: 0 | AW32: 0 | AX32: 0
A33: 006gK00000Po2FLQAZ | B33: Najd Retail Group – Data & Analytics 2026 | C33: Najd Retail Group | D33: Retail | E33: Saudi Arabia | F33: Corporate | G33: Suraj OD | H33: Proposal Submitted | I33: 0 | J33: 0 | K33: 0.6 | L33: 1200000 | M33: =L33*K33 -> 720000 | N33: 46319 | O33: Q4 | P33: 2026 | Q33: Best Case | R33: Existing Customer – Support | S33: Events & Campaigns | U33: Data & Analytics | V33: 46290 | AB33: 46219 | AC33: =IF(I33=1,N33-AB33,Overview!$B$5-AB33) -> 84 | AD33: ABA sample CSV | AE33: 0 | AF33: 0 | AG33: 0 | AH33: 0 | AI33: 1 | AJ33: 1 | AK33: 1 | AL33: 0 | AM33: 0 | AN33: 0 | AO33: 0 | AP33: 0 | AQ33: 1 | AR33: 0 | AS33: 0 | AT33: 1 | AU33: 0 | AV33: 0 | AW33: 0 | AX33: 0
A34: 006gK00000Po2FCQAZ | B34: Najd Retail Group – SAP SuccessFactors 2026 | C34: Najd Retail Group | D34: Retail | E34: Saudi Arabia | F34: Corporate | G34: Mohammed Alburayh | H34: Solutioning | I34: 0 | J34: 0 | K34: 0.2 | L34: 320000 | M34: =L34*K34 -> 64000 | N34: 46319 | O34: Q4 | P34: 2026 | Q34: Pipeline | R34: Existing Customer – Change Request | S34: Sales Outreach | U34: SAP SuccessFactors | V34: 46285 | AB34: 46232 | AC34: =IF(I34=1,N34-AB34,Overview!$B$5-AB34) -> 71 | AD34: ABA sample CSV | AE34: 0 | AF34: 0 | AG34: 0 | AH34: 0 | AI34: 1 | AJ34: 1 | AK34: 1 | AL34: 0 | AM34: 0 | AN34: 0 | AO34: 0 | AP34: 0 | AQ34: 0 | AR34: 0 | AS34: 0 | AT34: 1 | AU34: 0 | AV34: 0 | AW34: 0 | AX34: 0
A35: 006gK00000Po2FXQAZ | B35: Riyadh Smart Utilities – Data & Analytics 2026 | C35: Riyadh Smart Utilities | D35: Energy | E35: Saudi Arabia | F35: Enterprise | G35: Mohammed Alburayh | H35: Negotiation | I35: 0 | J35: 0 | K35: 0.75 | L35: 2200000 | M35: =L35*K35 -> 1650000 | N35: 46325 | O35: Q4 | P35: 2026 | Q35: Commit | R35: Existing Customer – New Opportunity | S35: Sales Outreach | U35: Data & Analytics | V35: 46295 | AB35: 46230 | AC35: =IF(I35=1,N35-AB35,Overview!$B$5-AB35) -> 73 | AD35: ABA sample CSV | AE35: 0 | AF35: 0 | AG35: 0 | AH35: 0 | AI35: 1 | AJ35: 1 | AK35: 1 | AL35: 0 | AM35: 0 | AN35: 0 | AO35: 0 | AP35: 0 | AQ35: 1 | AR35: 0 | AS35: 0 | AT35: 1 | AU35: 0 | AV35: 0 | AW35: 0 | AX35: 0
A36: 006gK00000Po2FKQAZ | B36: Taiba Education Co – Cloud Migration 2026 | C36: Taiba Education Co | D36: Education | E36: Saudi Arabia | F36: Corporate | G36: Venkatesh Rethinasamy | H36: Proposal Submitted | I36: 0 | J36: 0 | K36: 0.6 | L36: 250000 | M36: =L36*K36 -> 150000 | N36: 46334 | O36: Q4 | P36: 2026 | Q36: Best Case | R36: Existing Customer – Support | S36: Web | U36: Cloud Migration | V36: 46294 | AB36: 46230 | AC36: =IF(I36=1,N36-AB36,Overview!$B$5-AB36) -> 73 | AD36: ABA sample CSV | AE36: 0 | AF36: 0 | AG36: 0 | AH36: 0 | AI36: 1 | AJ36: 1 | AK36: 1 | AL36: 0 | AM36: 0 | AN36: 0 | AO36: 0 | AP36: 0 | AQ36: 0 | AR36: 0 | AS36: 0 | AT36: 1 | AU36: 0 | AV36: 0 | AW36: 0 | AX36: 0
A37: 006gK00000Po2FJQAZ | B37: Khaleej Finance House – Data & Analytics 2026 | C37: Khaleej Finance House | D37: Banking | E37: United Arab Emirates | F37: Enterprise | G37: Mohammed Alburayh | H37: Qualification | I37: 0 | J37: 0 | K37: 0.1 | L37: 3500000 | M37: =L37*K37 -> 350000 | N37: 46336 | O37: Q4 | P37: 2026 | Q37: Pipeline | R37: Existing Customer – New Opportunity | S37: Events & Campaigns | U37: Data & Analytics | V37: 46291 | AB37: 46234 | AC37: =IF(I37=1,N37-AB37,Overview!$B$5-AB37) -> 69 | AD37: ABA sample CSV | AE37: 0 | AF37: 0 | AG37: 0 | AH37: 0 | AI37: 1 | AJ37: 1 | AK37: 1 | AL37: 0 | AM37: 0 | AN37: 0 | AO37: 0 | AP37: 0 | AQ37: 0 | AR37: 0 | AS37: 0 | AT37: 1 | AU37: 0 | AV37: 0 | AW37: 0 | AX37: 0
A38: 006gK00000Po2FBQAZ | B38: Red Sea Logistics – Cloud Migration 2026 | C38: Red Sea Logistics | D38: Transportation | E38: Saudi Arabia | F38: Corporate | G38: Suraj OD | H38: Proposal Preparation | I38: 0 | J38: 0 | K38: 0.4 | L38: 3000000 | M38: =L38*K38 -> 1200000 | N38: 46349 | O38: Q4 | P38: 2026 | Q38: Pipeline | R38: Existing Customer – Change Request | S38: Sales Outreach | U38: Cloud Migration | V38: 46299 | AB38: 46253 | AC38: =IF(I38=1,N38-AB38,Overview!$B$5-AB38) -> 50 | AD38: ABA sample CSV | AE38: 0 | AF38: 0 | AG38: 0 | AH38: 0 | AI38: 1 | AJ38: 1 | AK38: 1 | AL38: 0 | AM38: 0 | AN38: 0 | AO38: 0 | AP38: 0 | AQ38: 0 | AR38: 0 | AS38: 0 | AT38: 1 | AU38: 0 | AV38: 0 | AW38: 0 | AX38: 0
A39: 006gK00000Po2FEQAZ | B39: Gulf Petrochem Services – SAP S/4HANA 2026 | C39: Gulf Petrochem Services | D39: Oil & Gas | E39: Saudi Arabia | F39: Enterprise | G39: Mohammed Alburayh | H39: Negotiation | I39: 0 | J39: 0 | K39: 0.75 | L39: 3500000 | M39: =L39*K39 -> 2625000 | N39: 46357 | O39: Q4 | P39: 2026 | Q39: Commit | R39: Existing Customer – Upgrade/Upsell | S39: SAP Leads | U39: SAP S/4HANA | V39: 46299 | AB39: 46232 | AC39: =IF(I39=1,N39-AB39,Overview!$B$5-AB39) -> 71 | AD39: ABA sample CSV | AE39: 0 | AF39: 0 | AG39: 0 | AH39: 0 | AI39: 1 | AJ39: 1 | AK39: 1 | AL39: 0 | AM39: 0 | AN39: 0 | AO39: 0 | AP39: 0 | AQ39: 0 | AR39: 0 | AS39: 0 | AT39: 1 | AU39: 0 | AV39: 0 | AW39: 0 | AX39: 0
A40: 006gK00000Po2FAQAZ | B40: Khaleej Finance House – SAP Support (AMS) 2026 | C40: Khaleej Finance House | D40: Banking | E40: United Arab Emirates | F40: Enterprise | G40: Mohammed Alburayh | H40: Qualification | I40: 0 | J40: 0 | K40: 0.1 | L40: 3000000 | M40: =L40*K40 -> 300000 | N40: 46366 | O40: Q4 | P40: 2026 | Q40: Pipeline | R40: Existing Customer – Upgrade/Upsell | S40: SAP Leads | U40: SAP Support (AMS) | V40: 46317 | AB40: 46278 | AC40: =IF(I40=1,N40-AB40,Overview!$B$5-AB40) -> 25 | AD40: ABA sample CSV | AE40: 0 | AF40: 0 | AG40: 0 | AH40: 0 | AI40: 1 | AJ40: 1 | AK40: 1 | AL40: 0 | AM40: 0 | AN40: 0 | AO40: 0 | AP40: 0 | AQ40: 0 | AR40: 0 | AS40: 0 | AT40: 1 | AU40: 0 | AV40: 0 | AW40: 1 | AX40: 0
A41: 006gK00000Po2FGQAZ | B41: Desert Bloom Foods – SAP Support (AMS) 2026 | C41: Desert Bloom Foods | D41: Food & Beverage | E41: Saudi Arabia | F41: SME | G41: Mohammed Alburayh | H41: Internal Review | I41: 0 | J41: 0 | K41: 0.5 | L41: 1500000 | M41: =L41*K41 -> 750000 | N41: 46372 | O41: Q4 | P41: 2026 | Q41: Pipeline | R41: Existing Customer – Support | S41: SAP Leads | U41: SAP Support (AMS) | V41: 46344 | AB41: 46291 | AC41: =IF(I41=1,N41-AB41,Overview!$B$5-AB41) -> 12 | AD41: ABA sample CSV | AE41: 0 | AF41: 0 | AG41: 0 | AH41: 0 | AI41: 1 | AJ41: 1 | AK41: 1 | AL41: 0 | AM41: 0 | AN41: 0 | AO41: 0 | AP41: 0 | AQ41: 0 | AR41: 0 | AS41: 0 | AT41: 1 | AU41: 0 | AV41: 0 | AW41: 0 | AX41: 0
A42: 006gK00000Po8C5QAJ | B42: Motiveminds Test Opportunity | C42: Motiveminds Test Account | G42: Suraj OD | H42: Prospecting | I42: 0 | J42: 0 | K42: 0.1 | L42: 1000 | M42: =L42*K42 -> 100 | N42: 46387 | O42: Q4 | P42: 2026 | Q42: Pipeline | AB42: 46303 | AC42: =IF(I42=1,N42-AB42,Overview!$B$5-AB42) -> 0 | AD42: Created manually in the org (not part of the build) | AE42: 0 | AF42: 0 | AG42: 0 | AH42: 0 | AI42: 1 | AJ42: 1 | AK42: 1 | AL42: 0 | AM42: 0 | AN42: 0 | AO42: 0 | AP42: 0 | AQ42: 0 | AR42: 0 | AS42: 0 | AT42: 1 | AU42: 0 | AV42: 0 | AW42: 0 | AX42: 0
A43: 006gK00000Po2FIQAZ | B43: Taiba Education Co – SAP S/4HANA 2027 | C43: Taiba Education Co | D43: Education | E43: Saudi Arabia | F43: Corporate | G43: Venkatesh Rethinasamy | H43: Verbal Award | I43: 0 | J43: 0 | K43: 0.9 | L43: 1200000 | M43: =L43*K43 -> 1080000 | N43: 46398 | O43: Q1 | P43: 2027 | Q43: Commit | R43: Existing Customer – Upgrade/Upsell | S43: Phone Inquiry | U43: SAP S/4HANA | V43: 46373 | AB43: 46281 | AC43: =IF(I43=1,N43-AB43,Overview!$B$5-AB43) -> 22 | AD43: ABA sample CSV | AE43: 0 | AF43: 0 | AG43: 0 | AH43: 0 | AI43: 1 | AJ43: 1 | AK43: 1 | AL43: 0 | AM43: 0 | AN43: 0 | AO43: 0 | AP43: 0 | AQ43: 0 | AR43: 0 | AS43: 0 | AT43: 0 | AU43: 0 | AV43: 0 | AW43: 0 | AX43: 0
A44: 006gK00000Po2F9QAJ | B44: Al Noor Healthcare – Cloud Migration 2027 | C44: Al Noor Healthcare | D44: Healthcare | E44: Saudi Arabia | F44: Enterprise | G44: Mohammed Alburayh | H44: Proposal Preparation | I44: 0 | J44: 0 | K44: 0.4 | L44: 450000 | M44: =L44*K44 -> 180000 | N44: 46409 | O44: Q1 | P44: 2027 | Q44: Pipeline | R44: Existing Customer – New Opportunity | S44: Web | U44: Cloud Migration | V44: 46354 | AB44: 46286 | AC44: =IF(I44=1,N44-AB44,Overview!$B$5-AB44) -> 17 | AD44: ABA sample CSV | AE44: 0 | AF44: 0 | AG44: 0 | AH44: 0 | AI44: 1 | AJ44: 1 | AK44: 1 | AL44: 0 | AM44: 0 | AN44: 0 | AO44: 0 | AP44: 0 | AQ44: 0 | AR44: 0 | AS44: 0 | AT44: 0 | AU44: 0 | AV44: 0 | AW44: 0 | AX44: 0
A45: 006gK00000Po2FTQAZ | B45: Khaleej Finance House – Cloud Migration 2027 | C45: Khaleej Finance House | D45: Banking | E45: United Arab Emirates | F45: Enterprise | G45: Suraj OD | H45: Deferred | I45: 0 | J45: 0 | K45: 0 | L45: 3500000 | M45: =L45*K45 -> 0 | N45: 46411 | O45: Q1 | P45: 2027 | Q45: Omitted | R45: Existing Customer – New Opportunity | S45: Events & Campaigns | U45: Cloud Migration | V45: 46362 | X45: Customer budget on hold | Y45: 46302 | AB45: 46266 | AC45: =IF(I45=1,N45-AB45,Overview!$B$5-AB45) -> 37 | AD45: ABA sample CSV | AE45: 0 | AF45: 0 | AG45: 0 | AH45: 0 | AI45: 0 | AJ45: 0 | AK45: 0 | AL45: 0 | AM45: 0 | AN45: 0 | AO45: 0 | AP45: 0 | AQ45: 0 | AR45: 0 | AS45: 1 | AT45: 0 | AU45: 0 | AV45: 0 | AW45: 0 | AX45: 0
A46: 006gK00000Po2FFQAZ | B46: Al Noor Healthcare – SAP SuccessFactors 2027 | C46: Al Noor Healthcare | D46: Healthcare | E46: Saudi Arabia | F46: Enterprise | G46: Mohammed Alburayh | H46: Proposal Preparation | I46: 0 | J46: 0 | K46: 0.4 | L46: 150000 | M46: =L46*K46 -> 60000 | N46: 46413 | O46: Q1 | P46: 2027 | Q46: Pipeline | R46: Existing Customer – Upgrade/Upsell | S46: Events & Campaigns | U46: SAP SuccessFactors | V46: 46370 | AB46: 46296 | AC46: =IF(I46=1,N46-AB46,Overview!$B$5-AB46) -> 7 | AD46: ABA sample CSV | AE46: 0 | AF46: 0 | AG46: 0 | AH46: 0 | AI46: 1 | AJ46: 1 | AK46: 1 | AL46: 0 | AM46: 0 | AN46: 0 | AO46: 0 | AP46: 0 | AQ46: 0 | AR46: 0 | AS46: 0 | AT46: 0 | AU46: 0 | AV46: 0 | AW46: 0 | AX46: 0
A47: 006gK00000Po2FNQAZ | B47: Taiba Education Co – SAP SuccessFactors 2027 | C47: Taiba Education Co | D47: Education | E47: Saudi Arabia | F47: Corporate | G47: Venkatesh Rethinasamy | H47: Proposal Submitted | I47: 0 | J47: 0 | K47: 0.6 | L47: 3500000 | M47: =L47*K47 -> 2100000 | N47: 46437 | O47: Q1 | P47: 2027 | Q47: Best Case | R47: Existing Customer – Change Request | S47: Phone Inquiry | U47: SAP SuccessFactors | V47: 46377 | AB47: 46296 | AC47: =IF(I47=1,N47-AB47,Overview!$B$5-AB47) -> 7 | AD47: ABA sample CSV | AE47: 0 | AF47: 0 | AG47: 0 | AH47: 0 | AI47: 1 | AJ47: 1 | AK47: 1 | AL47: 0 | AM47: 0 | AN47: 0 | AO47: 0 | AP47: 0 | AQ47: 0 | AR47: 0 | AS47: 0 | AT47: 0 | AU47: 0 | AV47: 0 | AW47: 0 | AX47: 0
A48: 006gK00000Po2FMQAZ | B48: Taiba Education Co – Data & Analytics 2027 | C48: Taiba Education Co | D48: Education | E48: Saudi Arabia | F48: Corporate | G48: Mohammed Alburayh | H48: Solutioning | I48: 0 | J48: 0 | K48: 0.2 | L48: 1500000 | M48: =L48*K48 -> 300000 | N48: 46446 | O48: Q1 | P48: 2027 | Q48: Pipeline | R48: Existing Customer – New Opportunity | S48: SAP Leads | U48: Data & Analytics | V48: 46393 | AB48: 46261 | AC48: =IF(I48=1,N48-AB48,Overview!$B$5-AB48) -> 42 | AD48: ABA sample CSV | AE48: 0 | AF48: 0 | AG48: 0 | AH48: 0 | AI48: 1 | AJ48: 1 | AK48: 1 | AL48: 0 | AM48: 0 | AN48: 0 | AO48: 0 | AP48: 0 | AQ48: 0 | AR48: 0 | AS48: 0 | AT48: 0 | AU48: 0 | AV48: 0 | AW48: 0 | AX48: 0
A49: 006gK00000Po2FSQAZ | B49: Al Noor Healthcare – SAP Support (AMS) 2027 | C49: Al Noor Healthcare | D49: Healthcare | E49: Saudi Arabia | F49: Enterprise | G49: Venkatesh Rethinasamy | H49: Deferred | I49: 0 | J49: 0 | K49: 0 | L49: 750000 | M49: =L49*K49 -> 0 | N49: 46449 | O49: Q1 | P49: 2027 | Q49: Omitted | R49: Existing Customer – Support | S49: Events & Campaigns | U49: SAP Support (AMS) | V49: 46401 | X49: Customer budget on hold | Y49: 46302 | AB49: 46271 | AC49: =IF(I49=1,N49-AB49,Overview!$B$5-AB49) -> 32 | AD49: ABA sample CSV | AE49: 0 | AF49: 0 | AG49: 0 | AH49: 0 | AI49: 0 | AJ49: 0 | AK49: 0 | AL49: 0 | AM49: 0 | AN49: 0 | AO49: 0 | AP49: 0 | AQ49: 0 | AR49: 0 | AS49: 1 | AT49: 0 | AU49: 0 | AV49: 0 | AW49: 0 | AX49: 0
A50: 006gK00000Po2FQQAZ | B50: Khaleej Finance House – SAP SuccessFactors 2027 | C50: Khaleej Finance House | D50: Banking | E50: United Arab Emirates | F50: Enterprise | G50: Suraj OD | H50: Deferred | I50: 0 | J50: 0 | K50: 0 | L50: 3500000 | M50: =L50*K50 -> 0 | N50: 46450 | O50: Q1 | P50: 2027 | Q50: Omitted | R50: Existing Customer – Upgrade/Upsell | S50: Sales Outreach | U50: SAP SuccessFactors | V50: 46400 | X50: Customer budget on hold | Y50: 46302 | AB50: 46281 | AC50: =IF(I50=1,N50-AB50,Overview!$B$5-AB50) -> 22 | AD50: ABA sample CSV | AE50: 0 | AF50: 0 | AG50: 0 | AH50: 0 | AI50: 0 | AJ50: 0 | AK50: 0 | AL50: 0 | AM50: 0 | AN50: 0 | AO50: 0 | AP50: 0 | AQ50: 0 | AR50: 0 | AS50: 1 | AT50: 0 | AU50: 0 | AV50: 0 | AW50: 0 | AX50: 0
A51: 006gK00000Po2FUQAZ | B51: Emirates Facility Mgmt – Data & Analytics 2027 | C51: Emirates Facility Mgmt | D51: Construction | E51: United Arab Emirates | F51: Corporate | G51: Venkatesh Rethinasamy | H51: Deferred | I51: 0 | J51: 0 | K51: 0 | L51: 250000 | M51: =L51*K51 -> 0 | N51: 46459 | O51: Q1 | P51: 2027 | Q51: Omitted | R51: Net New Names | S51: Partner Referral | U51: Data & Analytics | V51: 46420 | X51: Customer budget on hold | Y51: 46302 | AB51: 46261 | AC51: =IF(I51=1,N51-AB51,Overview!$B$5-AB51) -> 42 | AD51: ABA sample CSV | AE51: 0 | AF51: 0 | AG51: 0 | AH51: 0 | AI51: 0 | AJ51: 0 | AK51: 0 | AL51: 0 | AM51: 0 | AN51: 0 | AO51: 0 | AP51: 0 | AQ51: 0 | AR51: 0 | AS51: 1 | AT51: 0 | AU51: 0 | AV51: 0 | AW51: 0 | AX51: 0
A52: 006gK00000Po2FDQAZ | B52: Red Sea Logistics – Data & Analytics 2027 | C52: Red Sea Logistics | D52: Transportation | E52: Saudi Arabia | F52: Corporate | G52: Mohammed Alburayh | H52: Internal Review | I52: 0 | J52: 0 | K52: 0.5 | L52: 2200000 | M52: =L52*K52 -> 1100000 | N52: 46484 | O52: Q2 | P52: 2027 | Q52: Pipeline | R52: Existing Customer – New Opportunity | S52: Phone Inquiry | U52: Data & Analytics | V52: 46450 | AB52: 46266 | AC52: =IF(I52=1,N52-AB52,Overview!$B$5-AB52) -> 37 | AD52: ABA sample CSV | AE52: 0 | AF52: 0 | AG52: 0 | AH52: 0 | AI52: 1 | AJ52: 1 | AK52: 1 | AL52: 0 | AM52: 0 | AN52: 0 | AO52: 0 | AP52: 0 | AQ52: 0 | AR52: 0 | AS52: 0 | AT52: 0 | AU52: 0 | AV52: 0 | AW52: 0 | AX52: 0
A53: 006gK00000Po2FHQAZ | B53: Bahrain Telecom Partners – Data & Analytics 2027 | C53: Bahrain Telecom Partners | D53: Telecommunications | E53: Bahrain | F53: Corporate | G53: Mohammed Alburayh | H53: Internal Review | I53: 0 | J53: 0 | K53: 0.5 | L53: 1500000 | M53: =L53*K53 -> 750000 | N53: 46561 | O53: Q2 | P53: 2027 | Q53: Pipeline | R53: Existing Customer – Upgrade/Upsell | S53: Events & Campaigns | U53: Data & Analytics | V53: 46528 | AB53: 46286 | AC53: =IF(I53=1,N53-AB53,Overview!$B$5-AB53) -> 17 | AD53: ABA sample CSV | AE53: 0 | AF53: 0 | AG53: 0 | AH53: 0 | AI53: 1 | AJ53: 1 | AK53: 1 | AL53: 0 | AM53: 0 | AN53: 0 | AO53: 0 | AP53: 0 | AQ53: 0 | AR53: 0 | AS53: 0 | AT53: 0 | AU53: 0 | AV53: 0 | AW53: 0 | AX53: 0
A54: 006gK00000Po2FRQAZ | B54: Al Noor Healthcare – SAP SuccessFactors 2027 | C54: Al Noor Healthcare | D54: Healthcare | E54: Saudi Arabia | F54: Enterprise | G54: Suraj OD | H54: Deferred | I54: 0 | J54: 0 | K54: 0 | L54: 3500000 | M54: =L54*K54 -> 0 | N54: 46622 | O54: Q3 | P54: 2027 | Q54: Omitted | R54: Existing Customer – Support | S54: SAP Leads | U54: SAP SuccessFactors | V54: 46565 | X54: Customer budget on hold | Y54: 46302 | AB54: 46276 | AC54: =IF(I54=1,N54-AB54,Overview!$B$5-AB54) -> 27 | AD54: ABA sample CSV | AE54: 0 | AF54: 0 | AG54: 0 | AH54: 0 | AI54: 0 | AJ54: 0 | AK54: 0 | AL54: 0 | AM54: 0 | AN54: 0 | AO54: 0 | AP54: 0 | AQ54: 0 | AR54: 0 | AS54: 1 | AT54: 0 | AU54: 0 | AV54: 0 | AW54: 0 | AX54: 0

Sheet Report Results
A1: Report ID | B1: Report name | C1: Records (formula) | D1: Sum of Amount | E1: Sum of Expected Revenue | F1: Won records | G1: Closed records | H1: Win rate | I1: Average Amount | J1: Average Age (days) | K1: Live count from Salesforce | L1: Matches Salesforce? | M1: Note
A2: R01 | B2: Revenue Won – YTD by Quarter & Month | C2: =SUM('Opportunity Data'!$AE$2:$AE$54) -> 9 | D2: =SUMPRODUCT('Opportunity Data'!$AE$2:$AE$54,'Opportunity Data'!$L$2:$L$54) -> 8900000 | E2: =SUMPRODUCT('Opportunity Data'!$AE$2:$AE$54,'Opportunity Data'!$M$2:$M$54) -> 8900000 | F2: =SUMPRODUCT('Opportunity Data'!$AE$2:$AE$54,'Opportunity Data'!$J$2:$J$54) -> 9 | G2: =SUMPRODUCT('Opportunity Data'!$AE$2:$AE$54,'Opportunity Data'!$I$2:$I$54) -> 9 | H2: =IF(G2=0,"-",F2/G2) -> 1 | I2: =IF(C2=0,"-",D2/C2) -> 988888.89 | J2: =IF(C2=0,"-",SUMPRODUCT('Opportunity Data'!$AE$2:$AE$54,'Opportunity Data'!$AC$2:$AC$54)/C2) -> 91.666667 | K2: 9 | L2: =IF(C2=K2,"Yes","Check") -> Yes
A3: R02 | B3: Revenue Won – This Month (MTD) | C3: =SUM('Opportunity Data'!$AF$2:$AF$54) -> 2 | D3: =SUMPRODUCT('Opportunity Data'!$AF$2:$AF$54,'Opportunity Data'!$L$2:$L$54) -> 2750000 | E3: =SUMPRODUCT('Opportunity Data'!$AF$2:$AF$54,'Opportunity Data'!$M$2:$M$54) -> 2750000 | F3: =SUMPRODUCT('Opportunity Data'!$AF$2:$AF$54,'Opportunity Data'!$J$2:$J$54) -> 2 | G3: =SUMPRODUCT('Opportunity Data'!$AF$2:$AF$54,'Opportunity Data'!$I$2:$I$54) -> 2 | H3: =IF(G3=0,"-",F3/G3) -> 1 | I3: =IF(C3=0,"-",D3/C3) -> 1375000 | J3: =IF(C3=0,"-",SUMPRODUCT('Opportunity Data'!$AF$2:$AF$54,'Opportunity Data'!$AC$2:$AC$54)/C3) -> 84.5 | K3: 2 | L3: =IF(C3=K3,"Yes","Check") -> Yes
A4: R03 | B4: Revenue Won – This Quarter (QTD) | C4: =SUM('Opportunity Data'!$AG$2:$AG$54) -> 2 | D4: =SUMPRODUCT('Opportunity Data'!$AG$2:$AG$54,'Opportunity Data'!$L$2:$L$54) -> 2750000 | E4: =SUMPRODUCT('Opportunity Data'!$AG$2:$AG$54,'Opportunity Data'!$M$2:$M$54) -> 2750000 | F4: =SUMPRODUCT('Opportunity Data'!$AG$2:$AG$54,'Opportunity Data'!$J$2:$J$54) -> 2 | G4: =SUMPRODUCT('Opportunity Data'!$AG$2:$AG$54,'Opportunity Data'!$I$2:$I$54) -> 2 | H4: =IF(G4=0,"-",F4/G4) -> 1 | I4: =IF(C4=0,"-",D4/C4) -> 1375000 | J4: =IF(C4=0,"-",SUMPRODUCT('Opportunity Data'!$AG$2:$AG$54,'Opportunity Data'!$AC$2:$AC$54)/C4) -> 84.5 | K4: 2 | L4: =IF(C4=K4,"Yes","Check") -> Yes
A5: R04 | B5: Revenue Won – This Year vs Last Year | C5: =SUM('Opportunity Data'!$AH$2:$AH$54) -> 16 | D5: =SUMPRODUCT('Opportunity Data'!$AH$2:$AH$54,'Opportunity Data'!$L$2:$L$54) -> 16170000 | E5: =SUMPRODUCT('Opportunity Data'!$AH$2:$AH$54,'Opportunity Data'!$M$2:$M$54) -> 16170000 | F5: =SUMPRODUCT('Opportunity Data'!$AH$2:$AH$54,'Opportunity Data'!$J$2:$J$54) -> 16 | G5: =SUMPRODUCT('Opportunity Data'!$AH$2:$AH$54,'Opportunity Data'!$I$2:$I$54) -> 16 | H5: =IF(G5=0,"-",F5/G5) -> 1 | I5: =IF(C5=0,"-",D5/C5) -> 1010625 | J5: =IF(C5=0,"-",SUMPRODUCT('Opportunity Data'!$AH$2:$AH$54,'Opportunity Data'!$AC$2:$AC$54)/C5) -> 88.9375 | K5: 16 | L5: =IF(C5=K5,"Yes","Check") -> Yes
A6: R05 | B6: Open Pipeline by Stage | C6: =SUM('Opportunity Data'!$AI$2:$AI$54) -> 20 | D6: =SUMPRODUCT('Opportunity Data'!$AI$2:$AI$54,'Opportunity Data'!$L$2:$L$54) -> 31421000 | E6: =SUMPRODUCT('Opportunity Data'!$AI$2:$AI$54,'Opportunity Data'!$M$2:$M$54) -> 15224100 | F6: =SUMPRODUCT('Opportunity Data'!$AI$2:$AI$54,'Opportunity Data'!$J$2:$J$54) -> 0 | G6: =SUMPRODUCT('Opportunity Data'!$AI$2:$AI$54,'Opportunity Data'!$I$2:$I$54) -> 0 | H6: =IF(G6=0,"-",F6/G6) -> - | I6: =IF(C6=0,"-",D6/C6) -> 1571050 | J6: =IF(C6=0,"-",SUMPRODUCT('Opportunity Data'!$AI$2:$AI$54,'Opportunity Data'!$AC$2:$AC$54)/C6) -> 51.4 | K6: 20 | L6: =IF(C6=K6,"Yes","Check") -> Yes
A7: R06 | B7: Pipeline by Close Quarter (Next 4) | C7: =SUM('Opportunity Data'!$AJ$2:$AJ$54) -> 18 | D7: =SUMPRODUCT('Opportunity Data'!$AJ$2:$AJ$54,'Opportunity Data'!$L$2:$L$54) -> 30271000 | E7: =SUMPRODUCT('Opportunity Data'!$AJ$2:$AJ$54,'Opportunity Data'!$M$2:$M$54) -> 14549100 | F7: =SUMPRODUCT('Opportunity Data'!$AJ$2:$AJ$54,'Opportunity Data'!$J$2:$J$54) -> 0 | G7: =SUMPRODUCT('Opportunity Data'!$AJ$2:$AJ$54,'Opportunity Data'!$I$2:$I$54) -> 0 | H7: =IF(G7=0,"-",F7/G7) -> - | I7: =IF(C7=0,"-",D7/C7) -> 1681722.2 | J7: =IF(C7=0,"-",SUMPRODUCT('Opportunity Data'!$AJ$2:$AJ$54,'Opportunity Data'!$AC$2:$AC$54)/C7) -> 42.611111 | K7: 18 | L7: =IF(C7=K7,"Yes","Check") -> Yes
A8: R07 | B8: Pipeline by Salesperson & Stage | C8: =SUM('Opportunity Data'!$AK$2:$AK$54) -> 20 | D8: =SUMPRODUCT('Opportunity Data'!$AK$2:$AK$54,'Opportunity Data'!$L$2:$L$54) -> 31421000 | E8: =SUMPRODUCT('Opportunity Data'!$AK$2:$AK$54,'Opportunity Data'!$M$2:$M$54) -> 15224100 | F8: =SUMPRODUCT('Opportunity Data'!$AK$2:$AK$54,'Opportunity Data'!$J$2:$J$54) -> 0 | G8: =SUMPRODUCT('Opportunity Data'!$AK$2:$AK$54,'Opportunity Data'!$I$2:$I$54) -> 0 | H8: =IF(G8=0,"-",F8/G8) -> - | I8: =IF(C8=0,"-",D8/C8) -> 1571050 | J8: =IF(C8=0,"-",SUMPRODUCT('Opportunity Data'!$AK$2:$AK$54,'Opportunity Data'!$AC$2:$AC$54)/C8) -> 51.4 | K8: 20 | L8: =IF(C8=K8,"Yes","Check") -> Yes
A9: R08 | B9: Revenue Won by Salesperson – YTD | C9: =SUM('Opportunity Data'!$AL$2:$AL$54) -> 9 | D9: =SUMPRODUCT('Opportunity Data'!$AL$2:$AL$54,'Opportunity Data'!$L$2:$L$54) -> 8900000 | E9: =SUMPRODUCT('Opportunity Data'!$AL$2:$AL$54,'Opportunity Data'!$M$2:$M$54) -> 8900000 | F9: =SUMPRODUCT('Opportunity Data'!$AL$2:$AL$54,'Opportunity Data'!$J$2:$J$54) -> 9 | G9: =SUMPRODUCT('Opportunity Data'!$AL$2:$AL$54,'Opportunity Data'!$I$2:$I$54) -> 9 | H9: =IF(G9=0,"-",F9/G9) -> 1 | I9: =IF(C9=0,"-",D9/C9) -> 988888.89 | J9: =IF(C9=0,"-",SUMPRODUCT('Opportunity Data'!$AL$2:$AL$54,'Opportunity Data'!$AC$2:$AC$54)/C9) -> 91.666667 | K9: 9 | L9: =IF(C9=K9,"Yes","Check") -> Yes
A10: R09 | B10: Win Rate by Salesperson – YTD | C10: =SUM('Opportunity Data'!$AM$2:$AM$54) -> 15 | D10: =SUMPRODUCT('Opportunity Data'!$AM$2:$AM$54,'Opportunity Data'!$L$2:$L$54) -> 14720000 | E10: =SUMPRODUCT('Opportunity Data'!$AM$2:$AM$54,'Opportunity Data'!$M$2:$M$54) -> 8900000 | F10: =SUMPRODUCT('Opportunity Data'!$AM$2:$AM$54,'Opportunity Data'!$J$2:$J$54) -> 9 | G10: =SUMPRODUCT('Opportunity Data'!$AM$2:$AM$54,'Opportunity Data'!$I$2:$I$54) -> 15 | H10: =IF(G10=0,"-",F10/G10) -> 0.6 | I10: =IF(C10=0,"-",D10/C10) -> 981333.33 | J10: =IF(C10=0,"-",SUMPRODUCT('Opportunity Data'!$AM$2:$AM$54,'Opportunity Data'!$AC$2:$AC$54)/C10) -> 93.2 | K10: 15 | L10: =IF(C10=K10,"Yes","Check") -> Yes | M10: Win rate is the Win Rate % formula used by D1 and D2.
A11: R10 | B11: Win-Loss Analysis by Reason – YTD | C11: =SUM('Opportunity Data'!$AN$2:$AN$54) -> 15 | D11: =SUMPRODUCT('Opportunity Data'!$AN$2:$AN$54,'Opportunity Data'!$L$2:$L$54) -> 14720000 | E11: =SUMPRODUCT('Opportunity Data'!$AN$2:$AN$54,'Opportunity Data'!$M$2:$M$54) -> 8900000 | F11: =SUMPRODUCT('Opportunity Data'!$AN$2:$AN$54,'Opportunity Data'!$J$2:$J$54) -> 9 | G11: =SUMPRODUCT('Opportunity Data'!$AN$2:$AN$54,'Opportunity Data'!$I$2:$I$54) -> 15 | H11: =IF(G11=0,"-",F11/G11) -> 0.6 | I11: =IF(C11=0,"-",D11/C11) -> 981333.33 | J11: =IF(C11=0,"-",SUMPRODUCT('Opportunity Data'!$AN$2:$AN$54,'Opportunity Data'!$AC$2:$AC$54)/C11) -> 93.2 | K11: 15 | L11: =IF(C11=K11,"Yes","Check") -> Yes
A12: R10a | B12: Why We Win – YTD | C12: =SUM('Opportunity Data'!$AO$2:$AO$54) -> 9 | D12: =SUMPRODUCT('Opportunity Data'!$AO$2:$AO$54,'Opportunity Data'!$L$2:$L$54) -> 8900000 | E12: =SUMPRODUCT('Opportunity Data'!$AO$2:$AO$54,'Opportunity Data'!$M$2:$M$54) -> 8900000 | F12: =SUMPRODUCT('Opportunity Data'!$AO$2:$AO$54,'Opportunity Data'!$J$2:$J$54) -> 9 | G12: =SUMPRODUCT('Opportunity Data'!$AO$2:$AO$54,'Opportunity Data'!$I$2:$I$54) -> 9 | H12: =IF(G12=0,"-",F12/G12) -> 1 | I12: =IF(C12=0,"-",D12/C12) -> 988888.89 | J12: =IF(C12=0,"-",SUMPRODUCT('Opportunity Data'!$AO$2:$AO$54,'Opportunity Data'!$AC$2:$AC$54)/C12) -> 91.666667 | K12: 9 | L12: =IF(C12=K12,"Yes","Check") -> Yes
A13: R10b | B13: Why We Lose – YTD | C13: =SUM('Opportunity Data'!$AP$2:$AP$54) -> 6 | D13: =SUMPRODUCT('Opportunity Data'!$AP$2:$AP$54,'Opportunity Data'!$L$2:$L$54) -> 5820000 | E13: =SUMPRODUCT('Opportunity Data'!$AP$2:$AP$54,'Opportunity Data'!$M$2:$M$54) -> 0 | F13: =SUMPRODUCT('Opportunity Data'!$AP$2:$AP$54,'Opportunity Data'!$J$2:$J$54) -> 0 | G13: =SUMPRODUCT('Opportunity Data'!$AP$2:$AP$54,'Opportunity Data'!$I$2:$I$54) -> 6 | H13: =IF(G13=0,"-",F13/G13) -> 0 | I13: =IF(C13=0,"-",D13/C13) -> 970000 | J13: =IF(C13=0,"-",SUMPRODUCT('Opportunity Data'!$AP$2:$AP$54,'Opportunity Data'!$AC$2:$AC$54)/C13) -> 95.5 | K13: 6 | L13: =IF(C13=K13,"Yes","Check") -> Yes
A14: R11 | B14: Closing in Next 30 Days | C14: =SUM('Opportunity Data'!$AQ$2:$AQ$54) -> 3 | D14: =SUMPRODUCT('Opportunity Data'!$AQ$2:$AQ$54,'Opportunity Data'!$L$2:$L$54) -> 4700000 | E14: =SUMPRODUCT('Opportunity Data'!$AQ$2:$AQ$54,'Opportunity Data'!$M$2:$M$54) -> 3540000 | F14: =SUMPRODUCT('Opportunity Data'!$AQ$2:$AQ$54,'Opportunity Data'!$J$2:$J$54) -> 0 | G14: =SUMPRODUCT('Opportunity Data'!$AQ$2:$AQ$54,'Opportunity Data'!$I$2:$I$54) -> 0 | H14: =IF(G14=0,"-",F14/G14) -> - | I14: =IF(C14=0,"-",D14/C14) -> 1566666.7 | J14: =IF(C14=0,"-",SUMPRODUCT('Opportunity Data'!$AQ$2:$AQ$54,'Opportunity Data'!$AC$2:$AC$54)/C14) -> 82.333333 | K14: 3 | L14: =IF(C14=K14,"Yes","Check") -> Yes
A15: R12 | B15: Overdue & Stale Opportunities | C15: =SUM('Opportunity Data'!$AR$2:$AR$54) -> 2 | D15: =SUMPRODUCT('Opportunity Data'!$AR$2:$AR$54,'Opportunity Data'!$L$2:$L$54) -> 1150000 | E15: =SUMPRODUCT('Opportunity Data'!$AR$2:$AR$54,'Opportunity Data'!$M$2:$M$54) -> 675000 | F15: =SUMPRODUCT('Opportunity Data'!$AR$2:$AR$54,'Opportunity Data'!$J$2:$J$54) -> 0 | G15: =SUMPRODUCT('Opportunity Data'!$AR$2:$AR$54,'Opportunity Data'!$I$2:$I$54) -> 0 | H15: =IF(G15=0,"-",F15/G15) -> - | I15: =IF(C15=0,"-",D15/C15) -> 575000 | J15: =IF(C15=0,"-",SUMPRODUCT('Opportunity Data'!$AR$2:$AR$54,'Opportunity Data'!$AC$2:$AC$54)/C15) -> 130.5 | K15: 2 | L15: =IF(C15=K15,"Yes","Check") -> Yes
A16: R13 | B16: Deferred Opportunities | C16: =SUM('Opportunity Data'!$AS$2:$AS$54) -> 5 | D16: =SUMPRODUCT('Opportunity Data'!$AS$2:$AS$54,'Opportunity Data'!$L$2:$L$54) -> 11500000 | E16: =SUMPRODUCT('Opportunity Data'!$AS$2:$AS$54,'Opportunity Data'!$M$2:$M$54) -> 0 | F16: =SUMPRODUCT('Opportunity Data'!$AS$2:$AS$54,'Opportunity Data'!$J$2:$J$54) -> 0 | G16: =SUMPRODUCT('Opportunity Data'!$AS$2:$AS$54,'Opportunity Data'!$I$2:$I$54) -> 0 | H16: =IF(G16=0,"-",F16/G16) -> - | I16: =IF(C16=0,"-",D16/C16) -> 2300000 | J16: =IF(C16=0,"-",SUMPRODUCT('Opportunity Data'!$AS$2:$AS$54,'Opportunity Data'!$AC$2:$AC$54)/C16) -> 32 | K16: 5 | L16: =IF(C16=K16,"Yes","Check") -> Yes
A17: R14 | B17: Revenue & Pipeline by Type | C17: =SUM('Opportunity Data'!$AT$2:$AT$54) -> 22 | D17: =SUMPRODUCT('Opportunity Data'!$AT$2:$AT$54,'Opportunity Data'!$L$2:$L$54) -> 29821000 | E17: =SUMPRODUCT('Opportunity Data'!$AT$2:$AT$54,'Opportunity Data'!$M$2:$M$54) -> 18554100 | F17: =SUMPRODUCT('Opportunity Data'!$AT$2:$AT$54,'Opportunity Data'!$J$2:$J$54) -> 9 | G17: =SUMPRODUCT('Opportunity Data'!$AT$2:$AT$54,'Opportunity Data'!$I$2:$I$54) -> 9 | H17: =IF(G17=0,"-",F17/G17) -> 1 | I17: =IF(C17=0,"-",D17/C17) -> 1355500 | J17: =IF(C17=0,"-",SUMPRODUCT('Opportunity Data'!$AT$2:$AT$54,'Opportunity Data'!$AC$2:$AC$54)/C17) -> 77.454545 | K17: 22 | L17: =IF(C17=K17,"Yes","Check") -> Yes
A18: R15 | B18: Revenue by Lead Source & Campaign | C18: =SUM('Opportunity Data'!$AU$2:$AU$54) -> 9 | D18: =SUMPRODUCT('Opportunity Data'!$AU$2:$AU$54,'Opportunity Data'!$L$2:$L$54) -> 8900000 | E18: =SUMPRODUCT('Opportunity Data'!$AU$2:$AU$54,'Opportunity Data'!$M$2:$M$54) -> 8900000 | F18: =SUMPRODUCT('Opportunity Data'!$AU$2:$AU$54,'Opportunity Data'!$J$2:$J$54) -> 9 | G18: =SUMPRODUCT('Opportunity Data'!$AU$2:$AU$54,'Opportunity Data'!$I$2:$I$54) -> 9 | H18: =IF(G18=0,"-",F18/G18) -> 1 | I18: =IF(C18=0,"-",D18/C18) -> 988888.89 | J18: =IF(C18=0,"-",SUMPRODUCT('Opportunity Data'!$AU$2:$AU$54,'Opportunity Data'!$AC$2:$AC$54)/C18) -> 91.666667 | K18: 9 | L18: =IF(C18=K18,"Yes","Check") -> Yes
A19: R16 | B19: Revenue by Industry & Country | C19: =SUM('Opportunity Data'!$AV$2:$AV$54) -> 9 | D19: =SUMPRODUCT('Opportunity Data'!$AV$2:$AV$54,'Opportunity Data'!$L$2:$L$54) -> 8900000 | E19: =SUMPRODUCT('Opportunity Data'!$AV$2:$AV$54,'Opportunity Data'!$M$2:$M$54) -> 8900000 | F19: =SUMPRODUCT('Opportunity Data'!$AV$2:$AV$54,'Opportunity Data'!$J$2:$J$54) -> 9 | G19: =SUMPRODUCT('Opportunity Data'!$AV$2:$AV$54,'Opportunity Data'!$I$2:$I$54) -> 9 | H19: =IF(G19=0,"-",F19/G19) -> 1 | I19: =IF(C19=0,"-",D19/C19) -> 988888.89 | J19: =IF(C19=0,"-",SUMPRODUCT('Opportunity Data'!$AV$2:$AV$54,'Opportunity Data'!$AC$2:$AC$54)/C19) -> 91.666667 | K19: 9 | L19: =IF(C19=K19,"Yes","Check") -> Yes
A20: R17 | B20: Upcoming Proposal Submissions | C20: =SUM('Opportunity Data'!$AW$2:$AW$54) -> 1 | D20: =SUMPRODUCT('Opportunity Data'!$AW$2:$AW$54,'Opportunity Data'!$L$2:$L$54) -> 3000000 | E20: =SUMPRODUCT('Opportunity Data'!$AW$2:$AW$54,'Opportunity Data'!$M$2:$M$54) -> 300000 | F20: =SUMPRODUCT('Opportunity Data'!$AW$2:$AW$54,'Opportunity Data'!$J$2:$J$54) -> 0 | G20: =SUMPRODUCT('Opportunity Data'!$AW$2:$AW$54,'Opportunity Data'!$I$2:$I$54) -> 0 | H20: =IF(G20=0,"-",F20/G20) -> - | I20: =IF(C20=0,"-",D20/C20) -> 3000000 | J20: =IF(C20=0,"-",SUMPRODUCT('Opportunity Data'!$AW$2:$AW$54,'Opportunity Data'!$AC$2:$AC$54)/C20) -> 25 | K20: 1 | L20: =IF(C20=K20,"Yes","Check") -> Yes
A21: R18 | B21: Average Deal Size & Sales Cycle | C21: =SUM('Opportunity Data'!$AX$2:$AX$54) -> 10 | D21: =SUMPRODUCT('Opportunity Data'!$AX$2:$AX$54,'Opportunity Data'!$L$2:$L$54) -> 9650000 | E21: =SUMPRODUCT('Opportunity Data'!$AX$2:$AX$54,'Opportunity Data'!$M$2:$M$54) -> 9650000 | F21: =SUMPRODUCT('Opportunity Data'!$AX$2:$AX$54,'Opportunity Data'!$J$2:$J$54) -> 10 | G21: =SUMPRODUCT('Opportunity Data'!$AX$2:$AX$54,'Opportunity Data'!$I$2:$I$54) -> 10 | H21: =IF(G21=0,"-",F21/G21) -> 1 | I21: =IF(C21=0,"-",D21/C21) -> 965000 | J21: =IF(C21=0,"-",SUMPRODUCT('Opportunity Data'!$AX$2:$AX$54,'Opportunity Data'!$AC$2:$AC$54)/C21) -> 93.7 | K21: 10 | L21: =IF(C21=K21,"Yes","Check") -> Yes | M21: Average Amount and Average Age are the report's summaries.
A23: How it works | B23: Each figure is calculated from the 1/0 'In Rxx' flags on the Opportunity Data sheet. A flag is 1 when the opportunity meets the report's filters, read from Salesforce on the as-of date. 'Live count from Salesforce' is the record count returned by running the report itself.

Sheet Folders & Access
A1: Folder | B1: API name | C1: Folder type | D1: Shared with | E1: Contents
A2: ABA Management Reports | B2: ABA_Management_Reports | C2: Report folder | D2: View: role CEO and subordinates (internal) | E2: R01 Revenue Won – YTD by Quarter & Month, R02 Revenue Won – This Month (MTD), R03 Revenue Won – This Quarter (QTD), R04 Revenue Won – This Year vs Last Year, R05 Open Pipeline by Stage, R06 Pipeline by Close Quarter (Next 4), R14 Revenue & Pipeline by Type, R15 Revenue by Lead Source & Campaign, R16 Revenue by Industry & Country
A3: ABA Sales Reports | B3: ABA_Sales_Reports | C3: Report folder | D3: View: all internal users | E3: R07 Pipeline by Salesperson & Stage, R08 Revenue Won by Salesperson – YTD, R09 Win Rate by Salesperson – YTD, R10 Win-Loss Analysis by Reason – YTD, R10a Why We Win – YTD, R10b Why We Lose – YTD, R11 Closing in Next 30 Days, R12 Overdue & Stale Opportunities, R13 Deferred Opportunities, R17 Upcoming Proposal Submissions, R18 Average Deal Size & Sales Cycle
A4: ABA Management Dashboards | B4: ABA_Management_Dashboards | C4: Dashboard folder | D4: View: role CEO and subordinates (internal) | E4: D1 ABA Management – Revenue & Pipeline, D2 ABA Sales Performance & Win-Loss
A6: Dashboard viewing | D6: Both dashboards run as Suraj OD (System Administrator), so every viewer sees all opportunities.
